systems/tangnano20k_uart/rtl/fifo.v
module fifo #(
    parameter DATA_WIDTH = 8,       // Largura do dado (ex: 8 bits para um byte)
    parameter ADDR_WIDTH = 4        // Profundidade logarítmica (2^4 = 16 posições na fila)
)(
    input wire clk_i,               
    input wire rst_i,               // Reset global (ativo em nível baixo)
    
    // Porta de Escrita (Entrada de dados na Fila)
    input wire wr_en_i,             // Sinal de habilitação de escrita (Push)
    input wire [DATA_WIDTH-1:0] data_in_i, // Dado que será inserido na fila
    output wire full_o,             // Nível alto ('1') se a fila estiver totalmente cheia
    
    // Porta de Leitura (Saída de dados da Fila)
    input wire rd_en_i,             // Sinal de habilitação de leitura (Pop)
    output reg [DATA_WIDTH-1:0] data_out_o, // Dado retirado da fila
    output wire empty_o,            // Nível alto ('1') se a fila estiver vazia
    
    // Monitoramento
    output wire [ADDR_WIDTH:0] count_o  // Número atual de elementos dentro da fila
);

    // Calcula a profundidade máxima real da FIFO baseada no ADDR_WIDTH (ex: 2^4 = 16)
    localparam DEPTH = 1 << ADDR_WIDTH;  // deslocar o número 1 para a esquerda em ADDR_WIDTH posições - deslocado 4 vezes = 16 em decimal

    // Memória Interna (Buffer Circular)
    // Cria um vetor de registradores que age como a nossa "matriz" de armazenamento
    reg [DATA_WIDTH-1:0] mem [0:DEPTH-1];
    
    // Ponteiros e Contadores
    reg [ADDR_WIDTH-1:0] wr_ptr = 0;  // Ponteiro de escrita (aponta para onde o próximo dado será salvo) - endereços de escrita
    reg [ADDR_WIDTH-1:0] rd_ptr = 0;  // Ponteiro de leitura (aponta para onde o próximo dado será lido) - endereços de leitura
    reg [ADDR_WIDTH:0] count = 0;     // Contador de elementos presentes na fila - precisa contar até 16(0-15)

    // Sinais de Status (Flags)
    assign full_o  = (count == DEPTH);  // Fila cheia quando o contador atinge a capacidade máxima
    assign empty_o = (count == 0);      // Fila vazia quando o contador é zero
    assign count_o = count;             // Expõe a contagem atual para uso externo (se necessário)

    // Lógica de Escrita (Push)
    // Salva o dado na posição apontada por wr_ptr e incrementa o ponteiro circularmente
    always @(posedge clk_i or negedge rst_i) begin
        if (!rst_i) begin
            wr_ptr <= 0;
        end 
        else if (wr_en_i && !full_o) begin
            mem[wr_ptr] <= data_in_i;     // Escreve o dado na memória
            wr_ptr <= wr_ptr + 1'b1;      // Avança o ponteiro de escrita
        end
    end

    // Lógica de Leitura (Pop)
    // Retira o dado da posição apontada por rd_ptr e incrementa o ponteiro circularmente
    always @(posedge clk_i or negedge rst_i) begin
        if (!rst_i) begin
            rd_ptr <= 0;
            data_out_o <= {DATA_WIDTH{1'b0}};
        end 
        else if (rd_en_i && !empty_o) begin
            data_out_o <= mem[rd_ptr];    // Lê o dado da memória
            rd_ptr <= rd_ptr + 1'b1;      // Avança o ponteiro de leitura
        end
    end

    // Gerenciamento do Contador de Itens
    // Controla se a fila está ganhando, perdendo ou mantendo a quantidade de dados
    always @(posedge clk_i or negedge rst_i) begin
        if (!rst_i) begin
            count <= 0;
        end 
        else begin
            case ({wr_en_i && !full_o, rd_en_i && !empty_o})
                2'b10: count <= count + 1'b1; // Apenas escrevendo (Soma 1)
                2'b01: count <= count - 1'b1; // Apenas lendo (Subtrai 1)
                default: count <= count;      // Nenhum ou ambos ocorrem ao mesmo tempo (Mantém)
            endcase
        end
    end

endmodule

cores/uart_experiments/tb/tb_fifo.v
`timescale 1ns/1ps

module tb_fifo();

// ============================================================================
// Parâmetros e Sinais
// ============================================================================
parameter CLK_PERIOD = 20;          // Clock de 50 MHz -> 20 ns
parameter DATA_WIDTH = 8;
parameter ADDR_WIDTH = 4;
parameter DEPTH = 1 << ADDR_WIDTH;  // 16 posições

// Sinais do DUT
reg clk_i;
reg rst_i;
reg wr_en_i;
reg [DATA_WIDTH-1:0] data_in_i;
reg rd_en_i;
wire [DATA_WIDTH-1:0] data_out_o;
wire full_o;
wire empty_o;
wire [ADDR_WIDTH:0] count_o;

// Sinais auxiliares
integer errors = 0;
integer test_id = 0;
integer log_file;

// Instanciação do DUT
fifo #(
    .DATA_WIDTH(DATA_WIDTH),
    .ADDR_WIDTH(ADDR_WIDTH)
) dut_fifo (
    .clk_i(clk_i),
    .rst_i(rst_i),
    .wr_en_i(wr_en_i),
    .data_in_i(data_in_i),
    .full_o(full_o),
    .rd_en_i(rd_en_i),
    .data_out_o(data_out_o),
    .empty_o(empty_o),
    .count_o(count_o)
);

// ============================================================================
// Geração de Clock e Reset
// ============================================================================
initial clk_i = 1'b0;
always #(CLK_PERIOD/2) clk_i = ~clk_i;

// Reset inicial
initial begin
    rst_i = 1'b0;
    wr_en_i = 1'b0;
    data_in_i = 8'h00;
    rd_en_i = 1'b0;
    #100;
    rst_i = 1'b1;
end

// ============================================================================
// Tarefas de Suporte
// ============================================================================

// Tarefa para imprimir no console e no arquivo
task log_message;
    input string msg;
    begin
        $display("%s", msg);
        $fdisplay(log_file, "%s", msg);
    end
endtask

// Aplica reset por uma duração especificada em ciclos de clock
task apply_reset;
    input integer duration;
begin
    rst_i = 1'b0;
    repeat(duration) @(posedge clk_i);
    rst_i = 1'b1;
end
endtask

// Verifica um valor esperado contra o real e atualiza contador de erros
task check_value;
    input [31:0] expected;
    input [31:0] actual;
    input string description;
begin
    if (expected !== actual) begin
        log_message($sformatf("[ERRO] %s: esperado %h, obtido %h (tempo %0t)", description, expected, actual, $time));
        errors = errors + 1;
    end else begin
        log_message($sformatf("[OK]   %s (tempo %0t)", description, $time));
    end
end
endtask

// Escreve um dado na FIFO (push) e aguarda um ciclo de clock
task push;
    input [DATA_WIDTH-1:0] data;
begin
    wr_en_i = 1'b1;
    data_in_i = data;
    @(posedge clk_i);
    wr_en_i = 1'b0;
    @(posedge clk_i);  // aguarda um ciclo para estabilizar
end
endtask

// Lê um dado da FIFO (pop) e retorna o valor lido
task pop;
    output [DATA_WIDTH-1:0] data_out;
begin
    rd_en_i = 1'b1;
    @(posedge clk_i);
    rd_en_i = 1'b0;
    data_out = data_out_o;  // captura após o ciclo de leitura
    @(posedge clk_i);      // aguarda próximo ciclo para estabilizar flags
end
endtask

// ============================================================================
// Casos de Teste (TC-XX)
// ============================================================================

initial begin
    // Abrir arquivo de log
    log_file = $fopen("../sim/fifo_test_results.txt", "w");
    if (log_file == 0) begin
        $display("ERRO: Não foi possível criar o arquivo de log em ../sim/");
        $finish;
    end

    // Aguarda estabilização do reset
    #100;
    log_message("=============================================");
    log_message(" Testes da FIFO");
    log_message("=============================================");

    // TC-01: Estado inicial após reset
    test_id = 1;
    log_message($sformatf("\nTC-%0d: Estado inicial após reset", test_id));
    apply_reset(5);
    check_value(1'b1, empty_o, "empty_o em 1 após reset");
    check_value(1'b0, full_o, "full_o em 0 após reset");
    check_value(0, count_o, "count_o = 0 após reset");
    check_value(0, data_out_o, "data_out_o = 0 após reset");

    // TC-02: Escrita e leitura de um único dado
    test_id = 2;
    log_message($sformatf("\nTC-%0d: Escrita e leitura de um único dado", test_id));
    apply_reset(3);
    push(8'hA5);
    check_value(1, count_o, "count_o = 1 após push");
    check_value(1'b0, empty_o, "empty_o = 0 após push");
    begin
        reg [7:0] read_data;
        pop(read_data);
        check_value(8'hA5, read_data, "Dado lido corresponde ao escrito");
        check_value(0, count_o, "count_o = 0 após pop");
        check_value(1'b1, empty_o, "empty_o = 1 após pop");
    end

    // TC-03: Encher a FIFO completamente
    test_id = 3;
    log_message($sformatf("\nTC-%0d: Encher a FIFO completamente", test_id));
    apply_reset(3);
    for (int i = 0; i < DEPTH; i++) begin
        push(i[7:0]);
    end
    check_value(DEPTH, count_o, "count_o = 16 após encher");
    check_value(1'b1, full_o, "full_o = 1 quando cheia");
    check_value(1'b0, empty_o, "empty_o = 0 quando cheia");

    // TC-04: Esvaziar a FIFO completamente e verificar ordem
    test_id = 4;
    log_message($sformatf("\nTC-%0d: Esvaziar a FIFO e verificar ordem dos dados", test_id));
    for (int i = 0; i < DEPTH; i++) begin
        reg [7:0] read_data;
        pop(read_data);
        check_value(i[7:0], read_data, $sformatf("Dado %0d lido na ordem correta", i));
    end
    check_value(0, count_o, "count_o = 0 após esvaziar");
    check_value(1'b1, empty_o, "empty_o = 1 após esvaziar");
    check_value(1'b0, full_o, "full_o = 0 após esvaziar");

    // TC-05: Operações intercaladas (escrever, ler, escrever, ler)
    test_id = 5;
    log_message($sformatf("\nTC-%0d: Operações intercaladas", test_id));
    apply_reset(3);
    push(8'h11);
    push(8'h22);
    push(8'h33);
    begin
        reg [7:0] d;
        pop(d);
        check_value(8'h11, d, "Primeiro pop = 0x11");
    end
    push(8'h44);
    begin
        reg [7:0] d;
        pop(d);
        check_value(8'h22, d, "Segundo pop = 0x22");
        pop(d);
        check_value(8'h33, d, "Terceiro pop = 0x33");
        pop(d);
        check_value(8'h44, d, "Quarto pop = 0x44");
    end
    check_value(0, count_o, "FIFO vazia após operações intercaladas");
    check_value(1'b1, empty_o, "empty_o = 1 após esvaziar");

    // TC-06: Reset durante operação
    test_id = 6;
    log_message($sformatf("\nTC-%0d: Reset durante operação", test_id));
    apply_reset(3);
    push(8'hAA);
    push(8'hBB);
    // Aplica reset no meio
    rst_i = 1'b0;
    repeat(2) @(posedge clk_i);
    rst_i = 1'b1;
    check_value(0, count_o, "count_o = 0 após reset durante escrita");
    check_value(1'b1, empty_o, "empty_o = 1 após reset");
    check_value(1'b0, full_o, "full_o = 0 após reset");

    // TC-07: Escrita quando cheia (não deve alterar dados)
    test_id = 7;
    log_message($sformatf("\nTC-%0d: Escrita quando cheia", test_id));
    apply_reset(3);
    // Enche a FIFO
    for (int i = 0; i < DEPTH; i++) begin
        push(i[7:0]);
    end
    // Tenta escrever quando cheia
    wr_en_i = 1'b1;
    data_in_i = 8'hFF;
    @(posedge clk_i);
    wr_en_i = 1'b0;
    // Verifica que a FIFO não aceitou escrita (full permanece 1, count não aumentou)
    check_value(DEPTH, count_o, "count_o permanece 16 após tentativa de escrita com full");
    check_value(1'b1, full_o, "full_o permanece 1");
    // Esvazia e verifica que o último dado ainda é o 15
    for (int i = 0; i < DEPTH; i++) begin
        reg [7:0] d;
        pop(d);
        if (i == DEPTH-1)
            check_value(8'h0F, d, "Último dado é 0x0F (não sobrescrito)");
    end

    // TC-08: Leitura quando vazia (não deve alterar saída)
    test_id = 8;
    log_message($sformatf("\nTC-%0d: Leitura quando vazia", test_id));
    apply_reset(3);
    // FIFO vazia, tenta ler
    rd_en_i = 1'b1;
    @(posedge clk_i);
    rd_en_i = 1'b0;
    check_value(0, count_o, "count_o permanece 0");
    check_value(1'b1, empty_o, "empty_o permanece 1");
    check_value(0, data_out_o, "data_out_o permanece 0 (ou último valor)");

    // Resumo final
    log_message("\n=============================================");
    if (errors == 0)
        log_message("TODOS OS TESTES PASSARAM!");
    else
        log_message($sformatf("FALHAS: %0d erros encontrados", errors));
    log_message("=============================================");

    $fclose(log_file);
    $finish;
end

// ============================================================================
// Geração de VCD para visualização de ondas
// ============================================================================
initial begin
    $dumpfile("../sim/fifo_tb.vcd");
    $dumpvars(0, tb_fifo);
end

endmodule

cores/uart_experiments/sim/fifo_tb.vcd
$date
	Tue Sep  1 13:33:52 2026
$end
$version
	Icarus Verilog
$end
$timescale
	1ps
$end
$scope module tb_fifo $end
$var wire 1 ! full_o $end
$var wire 1 " empty_o $end
$var wire 8 # data_out_o [7:0] $end
$var wire 5 $ count_o [4:0] $end
$var parameter 32 % ADDR_WIDTH $end
$var parameter 32 & CLK_PERIOD $end
$var parameter 32 ' DATA_WIDTH $end
$var parameter 36 ( DEPTH $end
$var reg 1 ) clk_i $end
$var reg 8 * data_in_i [7:0] $end
$var reg 1 + rd_en_i $end
$var reg 1 , rst_i $end
$var reg 1 - wr_en_i $end
$var integer 32 . errors [31:0] $end
$var integer 32 / log_file [31:0] $end
$var integer 32 0 test_id [31:0] $end
$scope module dut_fifo $end
$var wire 1 ) clk_i $end
$var wire 5 1 count_o [4:0] $end
$var wire 8 2 data_in_i [7:0] $end
$var wire 1 + rd_en_i $end
$var wire 1 , rst_i $end
$var wire 1 - wr_en_i $end
$var wire 1 ! full_o $end
$var wire 1 " empty_o $end
$var parameter 32 3 ADDR_WIDTH $end
$var parameter 32 4 DATA_WIDTH $end
$var parameter 36 5 DEPTH $end
$var reg 5 6 count [4:0] $end
$var reg 8 7 data_out_o [7:0] $end
$var reg 4 8 rd_ptr [3:0] $end
$var reg 4 9 wr_ptr [3:0] $end
$upscope $end
$scope begin $ivl_for_loop0 $end
$var integer 32 : i [31:0] $end
$upscope $end
$scope begin $ivl_for_loop1 $end
$var integer 32 ; i [31:0] $end
$scope begin $unm_blk_13 $end
$var reg 8 < read_data [7:0] $end
$upscope $end
$upscope $end
$scope begin $ivl_for_loop2 $end
$var integer 32 = i [31:0] $end
$upscope $end
$scope begin $ivl_for_loop3 $end
$var integer 32 > i [31:0] $end
$scope begin $unm_blk_17 $end
$var reg 8 ? d [7:0] $end
$upscope $end
$upscope $end
$scope begin $unm_blk_11 $end
$var reg 8 @ read_data [7:0] $end
$upscope $end
$scope begin $unm_blk_14 $end
$var reg 8 A d [7:0] $end
$upscope $end
$scope begin $unm_blk_15 $end
$var reg 8 B d [7:0] $end
$upscope $end
$scope task apply_reset $end
$var integer 32 C duration [31:0] $end
$upscope $end
$scope task check_value $end
$var reg 32 D actual [31:0] $end
$var reg 32 E expected [31:0] $end
$upscope $end
$scope task log_message $end
$upscope $end
$scope task pop $end
$var reg 8 F data_out [7:0] $end
$upscope $end
$scope task push $end
$var reg 8 G data [7:0] $end
$upscope $end
$upscope $end
$enddefinitions $end
$comment Show the parameter values. $end
$dumpall
b10000 5
b1000 4
b100 3
b10000 (
b1000 '
b10100 &
b100 %
$end
#0
$dumpvars
bx G
bx F
bx E
bx D
bx C
bx B
bx A
bx @
bx ?
b0 >
b0 =
bx <
b0 ;
b0 :
b0 9
b0 8
b0 7
b0 6
b0 2
b0 1
b0 0
b10000000000000000000000000000011 /
b0 .
0-
0,
0+
b0 *
0)
b0 $
b0 #
1"
0!
$end
#10000
1)
#20000
0)
#30000
1)
#40000
0)
#50000
1)
#60000
0)
#70000
1)
#80000
0)
#90000
1)
#100000
0)
b101 C
b1 0
0,
#110000
1)
#120000
0)
#130000
1)
#140000
0)
#150000
1)
#160000
0)
#170000
1)
#180000
0)
#190000
b11 C
b10 0
b0 D
b0 E
0,
1)
#200000
0)
#210000
1)
#220000
0)
#230000
1)
#240000
0)
#250000
b1 9
0"
b1 $
b1 1
b1 6
b10100101 *
b10100101 2
1-
b10100101 G
1,
1)
#260000
0)
#270000
0-
1)
#280000
0)
#290000
b1 8
b10100101 #
b10100101 7
1"
b0 $
b0 1
b0 6
1+
b0 D
b0 E
1)
#300000
0)
#310000
b10100101 F
0+
1)
#320000
0)
#330000
b0 9
b0 #
b0 7
b0 8
0,
b11 0
b1 D
b1 E
b10100101 @
1)
#340000
0)
#350000
1)
#360000
0)
#370000
1)
#380000
0)
#390000
0"
b1 $
b1 1
b1 6
b1 9
b0 *
b0 2
1-
b0 G
1,
1)
#400000
0)
#410000
0-
1)
#420000
0)
#430000
b10 $
b10 1
b10 6
b10 9
b1 *
b1 2
1-
b1 G
b1 :
1)
#440000
0)
#450000
0-
1)
#460000
0)
#470000
b11 $
b11 1
b11 6
b11 9
b10 *
b10 2
1-
b10 G
b10 :
1)
#480000
0)
#490000
0-
1)
#500000
0)
#510000
b100 $
b100 1
b100 6
b100 9
b11 *
b11 2
1-
b11 G
b11 :
1)
#520000
0)
#530000
0-
1)
#540000
0)
#550000
b101 $
b101 1
b101 6
b101 9
b100 *
b100 2
1-
b100 G
b100 :
1)
#560000
0)
#570000
0-
1)
#580000
0)
#590000
b110 $
b110 1
b110 6
b110 9
b101 *
b101 2
1-
b101 G
b101 :
1)
#600000
0)
#610000
0-
1)
#620000
0)
#630000
b111 $
b111 1
b111 6
b111 9
b110 *
b110 2
1-
b110 G
b110 :
1)
#640000
0)
#650000
0-
1)
#660000
0)
#670000
b1000 $
b1000 1
b1000 6
b1000 9
b111 *
b111 2
1-
b111 G
b111 :
1)
#680000
0)
#690000
0-
1)
#700000
0)
#710000
b1001 $
b1001 1
b1001 6
b1001 9
b1000 *
b1000 2
1-
b1000 G
b1000 :
1)
#720000
0)
#730000
0-
1)
#740000
0)
#750000
b1010 $
b1010 1
b1010 6
b1010 9
b1001 *
b1001 2
1-
b1001 G
b1001 :
1)
#760000
0)
#770000
0-
1)
#780000
0)
#790000
b1011 $
b1011 1
b1011 6
b1011 9
b1010 *
b1010 2
1-
b1010 G
b1010 :
1)
#800000
0)
#810000
0-
1)
#820000
0)
#830000
b1100 $
b1100 1
b1100 6
b1100 9
b1011 *
b1011 2
1-
b1011 G
b1011 :
1)
#840000
0)
#850000
0-
1)
#860000
0)
#870000
b1101 $
b1101 1
b1101 6
b1101 9
b1100 *
b1100 2
1-
b1100 G
b1100 :
1)
#880000
0)
#890000
0-
1)
#900000
0)
#910000
b1110 $
b1110 1
b1110 6
b1110 9
b1101 *
b1101 2
1-
b1101 G
b1101 :
1)
#920000
0)
#930000
0-
1)
#940000
0)
#950000
b1111 $
b1111 1
b1111 6
b1111 9
b1110 *
b1110 2
1-
b1110 G
b1110 :
1)
#960000
0)
#970000
0-
1)
#980000
0)
#990000
1!
b10000 $
b10000 1
b10000 6
b0 9
b1111 *
b1111 2
1-
b1111 G
b1111 :
1)
#1000000
0)
#1010000
0-
1)
#1020000
0)
#1030000
0!
b1111 $
b1111 1
b1111 6
b1 8
1+
b100 0
b0 D
b0 E
b10000 :
1)
#1040000
0)
#1050000
b0 F
0+
1)
#1060000
0)
#1070000
b1110 $
b1110 1
b1110 6
b10 8
b1 #
b1 7
1+
b1 ;
b0 <
1)
#1080000
0)
#1090000
b1 F
0+
1)
#1100000
0)
#1110000
b1101 $
b1101 1
b1101 6
b11 8
b10 #
b10 7
1+
b10 ;
b1 D
b1 E
b1 <
1)
#1120000
0)
#1130000
b10 F
0+
1)
#1140000
0)
#1150000
b1100 $
b1100 1
b1100 6
b100 8
b11 #
b11 7
1+
b11 ;
b10 D
b10 E
b10 <
1)
#1160000
0)
#1170000
b11 F
0+
1)
#1180000
0)
#1190000
b1011 $
b1011 1
b1011 6
b101 8
b100 #
b100 7
1+
b100 ;
b11 D
b11 E
b11 <
1)
#1200000
0)
#1210000
b100 F
0+
1)
#1220000
0)
#1230000
b1010 $
b1010 1
b1010 6
b110 8
b101 #
b101 7
1+
b101 ;
b100 D
b100 E
b100 <
1)
#1240000
0)
#1250000
b101 F
0+
1)
#1260000
0)
#1270000
b1001 $
b1001 1
b1001 6
b111 8
b110 #
b110 7
1+
b110 ;
b101 D
b101 E
b101 <
1)
#1280000
0)
#1290000
b110 F
0+
1)
#1300000
0)
#1310000
b1000 $
b1000 1
b1000 6
b1000 8
b111 #
b111 7
1+
b111 ;
b110 D
b110 E
b110 <
1)
#1320000
0)
#1330000
b111 F
0+
1)
#1340000
0)
#1350000
b111 $
b111 1
b111 6
b1001 8
b1000 #
b1000 7
1+
b1000 ;
b111 D
b111 E
b111 <
1)
#1360000
0)
#1370000
b1000 F
0+
1)
#1380000
0)
#1390000
b110 $
b110 1
b110 6
b1010 8
b1001 #
b1001 7
1+
b1001 ;
b1000 D
b1000 E
b1000 <
1)
#1400000
0)
#1410000
b1001 F
0+
1)
#1420000
0)
#1430000
b101 $
b101 1
b101 6
b1011 8
b1010 #
b1010 7
1+
b1010 ;
b1001 D
b1001 E
b1001 <
1)
#1440000
0)
#1450000
b1010 F
0+
1)
#1460000
0)
#1470000
b100 $
b100 1
b100 6
b1100 8
b1011 #
b1011 7
1+
b1011 ;
b1010 D
b1010 E
b1010 <
1)
#1480000
0)
#1490000
b1011 F
0+
1)
#1500000
0)
#1510000
b11 $
b11 1
b11 6
b1101 8
b1100 #
b1100 7
1+
b1100 ;
b1011 D
b1011 E
b1011 <
1)
#1520000
0)
#1530000
b1100 F
0+
1)
#1540000
0)
#1550000
b10 $
b10 1
b10 6
b1110 8
b1101 #
b1101 7
1+
b1101 ;
b1100 D
b1100 E
b1100 <
1)
#1560000
0)
#1570000
b1101 F
0+
1)
#1580000
0)
#1590000
b1 $
b1 1
b1 6
b1111 8
b1110 #
b1110 7
1+
b1110 ;
b1101 D
b1101 E
b1101 <
1)
#1600000
0)
#1610000
b1110 F
0+
1)
#1620000
0)
#1630000
1"
b0 $
b0 1
b0 6
b0 8
b1111 #
b1111 7
1+
b1111 ;
b1110 D
b1110 E
b1110 <
1)
#1640000
0)
#1650000
b1111 F
0+
1)
#1660000
0)
#1670000
b0 #
b0 7
0,
b101 0
b10000 ;
b0 D
b0 E
b1111 <
1)
#1680000
0)
#1690000
1)
#1700000
0)
#1710000
1)
#1720000
0)
#1730000
b1 9
0"
b1 $
b1 1
b1 6
b10001 *
b10001 2
1-
b10001 G
1,
1)
#1740000
0)
#1750000
0-
1)
#1760000
0)
#1770000
b10 9
b10 $
b10 1
b10 6
b100010 *
b100010 2
1-
b100010 G
1)
#1780000
0)
#1790000
0-
1)
#1800000
0)
#1810000
b11 9
b11 $
b11 1
b11 6
b110011 *
b110011 2
1-
b110011 G
1)
#1820000
0)
#1830000
0-
1)
#1840000
0)
#1850000
b1 8
b10001 #
b10001 7
b10 $
b10 1
b10 6
1+
1)
#1860000
0)
#1870000
b10001 F
0+
1)
#1880000
0)
#1890000
b100 9
b11 $
b11 1
b11 6
b1000100 *
b1000100 2
1-
b1000100 G
b10001 D
b10001 E
b10001 A
1)
#1900000
0)
#1910000
0-
1)
#1920000
0)
#1930000
b10 8
b100010 #
b100010 7
b10 $
b10 1
b10 6
1+
1)
#1940000
0)
#1950000
b100010 F
0+
1)
#1960000
0)
#1970000
b11 8
b110011 #
b110011 7
b1 $
b1 1
b1 6
1+
b100010 D
b100010 E
b100010 B
1)
#1980000
0)
#1990000
b110011 F
0+
1)
#2000000
0)
#2010000
b100 8
b1000100 #
b1000100 7
1"
b0 $
b0 1
b0 6
1+
b110011 D
b110011 E
b110011 B
1)
#2020000
0)
#2030000
b1000100 F
0+
1)
#2040000
0)
#2050000
b0 9
b0 #
b0 7
b0 8
0,
b110 0
b1 D
b1 E
b1000100 B
1)
#2060000
0)
#2070000
1)
#2080000
0)
#2090000
1)
#2100000
0)
#2110000
0"
b1 $
b1 1
b1 6
b1 9
b10101010 *
b10101010 2
1-
b10101010 G
1,
1)
#2120000
0)
#2130000
0-
1)
#2140000
0)
#2150000
b10 $
b10 1
b10 6
b10 9
b10111011 *
b10111011 2
1-
b10111011 G
1)
#2160000
0)
#2170000
0-
1)
#2180000
0)
#2190000
1"
b0 $
b0 1
b0 6
b0 9
0,
1)
#2200000
0)
#2210000
1)
#2220000
0)
#2230000
b111 0
b0 D
b0 E
0,
1)
#2240000
0)
#2250000
1)
#2260000
0)
#2270000
1)
#2280000
0)
#2290000
b1 9
0"
b1 $
b1 1
b1 6
b0 *
b0 2
1-
b0 G
1,
1)
#2300000
0)
#2310000
0-
1)
#2320000
0)
#2330000
b10 9
b10 $
b10 1
b10 6
b1 *
b1 2
1-
b1 G
b1 =
1)
#2340000
0)
#2350000
0-
1)
#2360000
0)
#2370000
b11 9
b11 $
b11 1
b11 6
b10 *
b10 2
1-
b10 G
b10 =
1)
#2380000
0)
#2390000
0-
1)
#2400000
0)
#2410000
b100 9
b100 $
b100 1
b100 6
b11 *
b11 2
1-
b11 G
b11 =
1)
#2420000
0)
#2430000
0-
1)
#2440000
0)
#2450000
b101 9
b101 $
b101 1
b101 6
b100 *
b100 2
1-
b100 G
b100 =
1)
#2460000
0)
#2470000
0-
1)
#2480000
0)
#2490000
b110 9
b110 $
b110 1
b110 6
b101 *
b101 2
1-
b101 G
b101 =
1)
#2500000
0)
#2510000
0-
1)
#2520000
0)
#2530000
b111 9
b111 $
b111 1
b111 6
b110 *
b110 2
1-
b110 G
b110 =
1)
#2540000
0)
#2550000
0-
1)
#2560000
0)
#2570000
b1000 9
b1000 $
b1000 1
b1000 6
b111 *
b111 2
1-
b111 G
b111 =
1)
#2580000
0)
#2590000
0-
1)
#2600000
0)
#2610000
b1001 9
b1001 $
b1001 1
b1001 6
b1000 *
b1000 2
1-
b1000 G
b1000 =
1)
#2620000
0)
#2630000
0-
1)
#2640000
0)
#2650000
b1010 9
b1010 $
b1010 1
b1010 6
b1001 *
b1001 2
1-
b1001 G
b1001 =
1)
#2660000
0)
#2670000
0-
1)
#2680000
0)
#2690000
b1011 9
b1011 $
b1011 1
b1011 6
b1010 *
b1010 2
1-
b1010 G
b1010 =
1)
#2700000
0)
#2710000
0-
1)
#2720000
0)
#2730000
b1100 9
b1100 $
b1100 1
b1100 6
b1011 *
b1011 2
1-
b1011 G
b1011 =
1)
#2740000
0)
#2750000
0-
1)
#2760000
0)
#2770000
b1101 9
b1101 $
b1101 1
b1101 6
b1100 *
b1100 2
1-
b1100 G
b1100 =
1)
#2780000
0)
#2790000
0-
1)
#2800000
0)
#2810000
b1110 9
b1110 $
b1110 1
b1110 6
b1101 *
b1101 2
1-
b1101 G
b1101 =
1)
#2820000
0)
#2830000
0-
1)
#2840000
0)
#2850000
b1111 9
b1111 $
b1111 1
b1111 6
b1110 *
b1110 2
1-
b1110 G
b1110 =
1)
#2860000
0)
#2870000
0-
1)
#2880000
0)
#2890000
b0 9
1!
b10000 $
b10000 1
b10000 6
b1111 *
b1111 2
1-
b1111 G
b1111 =
1)
#2900000
0)
#2910000
0-
1)
#2920000
0)
#2930000
b11111111 *
b11111111 2
1-
b10000 =
1)
#2940000
0)
#2950000
0!
b1111 $
b1111 1
b1111 6
b1 8
1+
b1 D
b1 E
0-
1)
#2960000
0)
#2970000
b0 F
0+
1)
#2980000
0)
#2990000
b1110 $
b1110 1
b1110 6
b10 8
b1 #
b1 7
1+
b1 >
b0 ?
1)
#3000000
0)
#3010000
b1 F
0+
1)
#3020000
0)
#3030000
b1101 $
b1101 1
b1101 6
b11 8
b10 #
b10 7
1+
b10 >
b1 ?
1)
#3040000
0)
#3050000
b10 F
0+
1)
#3060000
0)
#3070000
b1100 $
b1100 1
b1100 6
b100 8
b11 #
b11 7
1+
b11 >
b10 ?
1)
#3080000
0)
#3090000
b11 F
0+
1)
#3100000
0)
#3110000
b1011 $
b1011 1
b1011 6
b101 8
b100 #
b100 7
1+
b100 >
b11 ?
1)
#3120000
0)
#3130000
b100 F
0+
1)
#3140000
0)
#3150000
b1010 $
b1010 1
b1010 6
b110 8
b101 #
b101 7
1+
b101 >
b100 ?
1)
#3160000
0)
#3170000
b101 F
0+
1)
#3180000
0)
#3190000
b1001 $
b1001 1
b1001 6
b111 8
b110 #
b110 7
1+
b110 >
b101 ?
1)
#3200000
0)
#3210000
b110 F
0+
1)
#3220000
0)
#3230000
b1000 $
b1000 1
b1000 6
b1000 8
b111 #
b111 7
1+
b111 >
b110 ?
1)
#3240000
0)
#3250000
b111 F
0+
1)
#3260000
0)
#3270000
b111 $
b111 1
b111 6
b1001 8
b1000 #
b1000 7
1+
b1000 >
b111 ?
1)
#3280000
0)
#3290000
b1000 F
0+
1)
#3300000
0)
#3310000
b110 $
b110 1
b110 6
b1010 8
b1001 #
b1001 7
1+
b1001 >
b1000 ?
1)
#3320000
0)
#3330000
b1001 F
0+
1)
#3340000
0)
#3350000
b101 $
b101 1
b101 6
b1011 8
b1010 #
b1010 7
1+
b1010 >
b1001 ?
1)
#3360000
0)
#3370000
b1010 F
0+
1)
#3380000
0)
#3390000
b100 $
b100 1
b100 6
b1100 8
b1011 #
b1011 7
1+
b1011 >
b1010 ?
1)
#3400000
0)
#3410000
b1011 F
0+
1)
#3420000
0)
#3430000
b11 $
b11 1
b11 6
b1101 8
b1100 #
b1100 7
1+
b1100 >
b1011 ?
1)
#3440000
0)
#3450000
b1100 F
0+
1)
#3460000
0)
#3470000
b10 $
b10 1
b10 6
b1110 8
b1101 #
b1101 7
1+
b1101 >
b1100 ?
1)
#3480000
0)
#3490000
b1101 F
0+
1)
#3500000
0)
#3510000
b1 $
b1 1
b1 6
b1111 8
b1110 #
b1110 7
1+
b1110 >
b1101 ?
1)
#3520000
0)
#3530000
b1110 F
0+
1)
#3540000
0)
#3550000
1"
b0 $
b0 1
b0 6
b0 8
b1111 #
b1111 7
1+
b1111 >
b1110 ?
1)
#3560000
0)
#3570000
b1111 F
0+
1)
#3580000
0)
#3590000
b0 #
b0 7
0,
b1000 0
b10000 >
b1111 D
b1111 E
b1111 ?
1)
#3600000
0)
#3610000
1)
#3620000
0)
#3630000
1)
#3640000
0)
#3650000
1+
1,
1)
#3660000
0)
#3670000
b0 D
b0 E
0+
1)
