cores/uart_experiments/rtl/rx copy.v
module rx (
    input wire clk_i, // entrada do clk_i
    input wire rst_i, // entrada do reset
    input wire enable_rx, // enable para recebimento
    input wire baud_tick, // tick rate
    input wire uart_rx_i, // entrada de dados que vem por um fio

    output reg [7:0] data_o, // saida de dados para um buffer de 1 byte
    output wire rx_valid // saida para indicar que o recebimento foi concluido
);

// Parâmetros para FSM
parameter IDLE = 2'b00, START = 2'b01, DATA = 2'b10, STOP = 2'b11;

// Registradores
reg [1:0] atual, proximo;              // dois registradores de dois bits para cada registrador: atual e próximo
reg [3:0] bit_count;                    // contador de bits de dados (0-7)
reg [3:0] tick_count;                 // contador de ticks (para sampling no meio do bit)

// Sincronização do sinal de entrada (debouncing)
reg rs232_t, rs232_t1, rs232_t2;
always @(posedge clk_i or negedge rst_i) begin
    if (!rst_i) begin
        rs232_t <= 1'b1;
        rs232_t1 <= 1'b1;
        rs232_t2 <= 1'b1;
    end
    else begin
        rs232_t <= uart_rx_i;
        rs232_t1 <= rs232_t;
        rs232_t2 <= rs232_t1;
    end
end

// FSM
always @(posedge clk_i or negedge rst_i) begin
    if (!rst_i)
        atual <= IDLE;
    else if (baud_tick || atual == IDLE)
    // else if (baud_tick)
        atual <= proximo;
end

// Lógica combinacional - Decisão do próximo estado
// Transmissão começa com o fio serial em 0
always @(*) begin
    case(atual)
        IDLE:
            if(!rs232_t2 && enable_rx)
                proximo = START;
            else
                proximo = IDLE;
        START:
            /*
            if(tick_count == 4'b0111)
                proximo = DATA;
            else
                proximo = START;
            */
            /*
            if (tick_count == 4'b0111) begin
                if (!rs232_t2)
                    proximo = DATA;
                else
                    proximo = IDLE;
            end
            else
                proximo = START;
            */
            if (tick_count == 4'b0111) begin
                if (!rs232_t2)
                    proximo = DATA;   // start bit confirmado
                else
                    proximo = IDLE;   // start bit inválido (glitch)
            end else begin
                if (!rs232_t2)
                    proximo = START;
                else
                    proximo = IDLE;   // linha voltou a 1 antes do tempo
            end
        DATA:
            if(bit_count == 4'b1000)
                proximo = STOP;
            else
                proximo = DATA;
            
            /*
            if (bit_count == 4'd7 && tick_count == 4'b1111)
                proximo = STOP;
            else
                proximo = DATA;
            */
        STOP:
            if(tick_count == 4'b1111)
                proximo = IDLE;
            else
                proximo = STOP;
        default:
            proximo = IDLE;
    endcase
end

// Lógica de recepção - Executa a cada baud_tick
// Lógica de recepção e contadores (Sincronizado com clk_i)
always @(posedge clk_i or negedge rst_i) begin
    if (!rst_i) begin
        tick_count <= 4'b0000;
        bit_count  <= 4'b0000;
    end
    else if (baud_tick) begin
        if (atual != IDLE) begin
            tick_count <= tick_count + 1;
            
            // Zera o tick na transição START -> DATA para alinhar a amostragem
            if (atual == START && tick_count == 4'b0111) begin
                tick_count <= 4'b0000;
            end
            else if (atual == DATA && tick_count == 4'b1111) begin
                bit_count <= bit_count + 1;
                tick_count <= 4'b0000;
            end
        end
        else begin
            tick_count <= 4'b0000;
            bit_count  <= 4'b0000; 
        end
    end
end

/*
// Lógica de contagem de ticks e bits cadenciada pelo baud_tick
always @(posedge clk_i or negedge rst_i) begin
    if (!rst_i) begin
        tick_count <= 4'b0000;
        bit_count  <= 4'b0000;
    end
    else if (baud_tick) begin
        if (atual == IDLE) begin
            tick_count <= 4'b0000;
            bit_count  <= 4'b0000;
        end
        else begin
            if (tick_count == 4'b1111) begin
                tick_count <= 4'b0000;
                if (atual == DATA) begin
                    bit_count <= bit_count + 1'b1;
                end
            end
            else begin
                tick_count <= tick_count + 1'b1;
            end
        end
    end
end
*/

// Dados recebidos pelo canal para o registrador
always @(posedge clk_i or negedge rst_i) begin
    if (!rst_i)
        data_o <= 8'd0;
    // O baud_tick garante que a captura ocorre apenas 1 vez na amostragem correta
    else if(baud_tick && atual == DATA && tick_count == 4'b1111) begin           
        case(bit_count)                         
            4'd0: data_o[0] <= rs232_t2;
            4'd1: data_o[1] <= rs232_t2;
            4'd2: data_o[2] <= rs232_t2;
            4'd3: data_o[3] <= rs232_t2;
            4'd4: data_o[4] <= rs232_t2;
            4'd5: data_o[5] <= rs232_t2;
            4'd6: data_o[6] <= rs232_t2;
            4'd7: data_o[7] <= rs232_t2;
            default: data_o <= data_o;
        endcase
    end
end

// Sinal de conclusão
assign rx_valid = (atual == STOP && tick_count == 4'b1111);

endmodule

cores/uart_experiments/rtl/tx copy.v
module tx (
    input wire clk_i, // clk_i do dispositivo
    input wire rst_i, // reset do circuito
    input wire enable_tx, // transmissao habilitada
    input wire baud_tick, // baud_tick da transmissão
    input wire [7:0] data_i, // entrada dos dados a serem transmitidos

    output reg uart_tx_o, // saida dos dados transmitidos interface rs232
    output wire tx_valid // concluiu transmissao
);

// variaveis da FSM
parameter IDLE = 2'b00, START = 2'b01, DATA = 2'b10, STOP = 2'b11;  // Quatro atuals para a transmissão

// Registradores
reg [1:0] atual, proximo;             // registrador para estado (2 bits)
reg [3:0] bit_count;                // até 8 bits de dados
reg [3:0] tick_count;               // contador de ticks para sincronização
reg [7:0] tx_data;                    // registra os dados de entrada

// FSM - cada bloco (TX,RX) possui uma FSM própria
always @ (posedge clk_i or negedge rst_i)			//Boa prática considera o reset
    begin
        if (!rst_i)	
            atual <= IDLE;				// Se botão de reset ativo, vai para idle
        else if (baud_tick || atual == IDLE)		
            atual <= proximo;			// Senão, vai para o próximo atual
    end

// Lógica combinacional - Decisão do próximo atual
always @(*) begin
    case(atual)
        IDLE:
            if(enable_tx)
                proximo = START;        // Habilita transmissão
            else
                proximo = IDLE;
        START:
            if(tick_count == 4'b1111)
                proximo = DATA;         // Após start bit, vai para dados
            else
                proximo = START;
        DATA:
            if(bit_count == 4'b1000)  // 8 bits transmitidos
                proximo = STOP;         // Vai para paridade + stop
            else
                proximo = DATA;
        STOP:
            if(tick_count == 4'b1111)
                proximo = IDLE;         // Transmissão completa
            else
                proximo = STOP;
        default:
            proximo = IDLE;
    endcase
end

// Registra dados de entrada quando habilitado para transmissão
always @ (posedge clk_i or negedge rst_i) begin
    if (!rst_i) begin
        tx_data <= 8'b00000000;
    end
    else if(atual == IDLE && enable_tx) begin
        tx_data <= data_i;
    end
end

// Lógica de sincronização com baud_tick
// Lógica de sincronização (Sincronizado com clk_i)
always @ (posedge clk_i or negedge rst_i) begin
    if (!rst_i) begin
        tick_count <= 4'b0000;
        bit_count <= 4'b0000;
    end
    else if (baud_tick) begin
        if (atual != IDLE) begin
            tick_count <= tick_count + 1;
            
            if (atual == START && tick_count == 4'b1111) begin
                tick_count <= 4'b0000;
                bit_count <= 4'b0000;
            end
            
            if (atual == DATA && tick_count == 4'b1111) begin
                bit_count <= bit_count + 1;
                tick_count <= 4'b0000;
            end
        end
        else begin
            tick_count <= 4'b0000;
            bit_count <= 4'b0000;
        end
    end
end

// Transmissão dos dados: START → 8 bits DATA → STOP (sem parity)
// Interface RS232 para transmissão em linha única
always@ (posedge clk_i or negedge rst_i) begin
    if (!rst_i)
        uart_tx_o <= 1'b1;               // se reset, fio fica em 1 (idle)
    else if(atual == START) begin
        uart_tx_o <= 1'b0;               // start bit sai imediatamente!
    end
    else if(atual == DATA) begin
        case(bit_count)               // envia os 8 bits
            4'd0: uart_tx_o <= tx_data[0];
            4'd1: uart_tx_o <= tx_data[1];
            4'd2: uart_tx_o <= tx_data[2];
            4'd3: uart_tx_o <= tx_data[3];
            4'd4: uart_tx_o <= tx_data[4];
            4'd5: uart_tx_o <= tx_data[5];
            4'd6: uart_tx_o <= tx_data[6];
            4'd7: uart_tx_o <= tx_data[7];
            default: uart_tx_o <= 1'b1;
        endcase
    end
    else if (atual == STOP) begin
        uart_tx_o <= 1'b1;               // stop bit
    end
    else if (atual == IDLE) begin
        uart_tx_o <= 1'b1;               // stop bit e idle ficam em 1
    end
end

// Sinal de conclusão de transmissão
assign tx_valid = (atual == IDLE);

endmodule

systems/tangnano20k_uart/final/baud_generate.v
module baud_generate #(
    parameter BAUD_RATE = 115200,     
    parameter CLK_FREQ = 27_000_000    
) (
    input wire clk_i,
    input wire rst_i,
    
    output wire baud_tick
);

    // Calcula o divisor para 16x Oversampling com ARREDONDAMENTO:
    // A soma de "(BAUD_RATE * 8)" equivale a somar 0.5 antes de dividir.
    // Assim, 14.64 vira 15.14, e ao truncar, o Verilog crava no 15 correto!
    
    localparam DIVISOR = (CLK_FREQ + (BAUD_RATE * 8)) / (BAUD_RATE * 16);
    
    reg [24:0] contador_baud;
    
    always @(posedge clk_i or negedge rst_i) begin
        if (!rst_i) begin
            contador_baud <= 25'b0;
        end
        else if (contador_baud >= DIVISOR - 1) begin
            contador_baud <= 25'b0;
        end
        else begin
            contador_baud <= contador_baud + 1'b1;
        end
    end
    
    // Gera um pulso (baud_tick) a cada DIVISOR clocks (16 pulsos formam 1 bit)
    assign baud_tick = (contador_baud == DIVISOR - 1) ? 1'b1 : 1'b0;

endmodule

cores/uart_experiments/rtl/uart.v
module uart #(
    parameter BAUD_RATE = 115200,           // velocidade UART
    parameter CLK_FREQ = 27_000_000,      // frequência do clock (27MHz para Tang Nano 20K)
    parameter ENABLE_RX = 1'b1,
    parameter ENABLE_TX = 1'b1
)(
    // Fios de entrada fundamentais
    input wire clk_i,                         // clock principal
    input wire rst_i,                         // reset global

    // Sinais para comunicação entre a UART e o computador
    input wire uart_rx_i,         // sinal serial RX
    output wire uart_tx_o,         // sinal serial TX

    // Sinais para dentro do CHIP
    input wire [7:0] tx_data_i,    // o byte que o hardware enviará para o PC
    input wire tx_send_i,          // O gatilho do hardware para enviar
    output wire tx_ready_o,

    output wire [7:0] rx_data_o,   // Entrega o byte que chegou do PC para o hardware
    output wire rx_valid_o          // Pulso avisando o hardware que chegou
);

// SINAIS INTERNOS
wire baud_tick;    

// GERADOR DE BAUD RATE
baud_generate #(
    .BAUD_RATE(BAUD_RATE),
    .CLK_FREQ(CLK_FREQ)
) baud_gen (
    .clk_i(clk_i),
    .rst_i(rst_i),
    .baud_tick(baud_tick)
);

// Transmissor, recebe os dados do CHIP e transmite
generate
    if (ENABLE_TX == 1'b1) begin: gen_tx // todo bloco begin ... end dentro de um generate é obrigado a ter um nome (alias), sendo gen_tx
        tx tx_instance (
            .clk_i(clk_i),
            .rst_i(rst_i),
            .enable_tx(tx_send_i),     // Ligado direto na porta de entrada

            .baud_tick(baud_tick),
            .data_i(tx_data_i),        // Ligado direto na porta de entrada

            .uart_tx_o(uart_tx_o),
            .tx_valid(tx_ready_o)        // Nossa porta vital (Não esqueça de declarar ela lá em cima!)
        );
    end
    else begin: gen_not_tx  // Se o TX estiver desativado, devemos manter a linha em '1' (estado de repouso da UART)
        assign uart_tx_o = 1'b1;
        assign tx_ready_o = 1'b0;
    end
endgenerate


// Receptor, recebe os dados e manda para o CHIP
generate
    if (ENABLE_RX == 1'b1) begin: gen_rx  // todo bloco begin ... end dentro de um generate é obrigado a ter um nome (alias), sendo gen_tx
        rx rx_instance (
            .clk_i(clk_i),
            .rst_i(rst_i),
            .enable_rx(1'b1),     // sempre ativo

            .baud_tick(baud_tick),
            .uart_rx_i(uart_rx_i),

            .data_o(rx_data_o),        // Ligado direto na porta de saída
            .rx_valid(rx_valid_o)        // Ligado direto na porta de saída
        );
    end
    else begin: gen_not_rx  // Se o RX estiver desativado, mantemos as saídas zeradas
        assign rx_data_o = 8'b0;
        assign rx_valid_o = 1'b0;
    end

endgenerate

endmodule

cores/uart_experiments/tb/tb_uart.v
`timescale 1ns/1ps

module tb_uart();

// ============================================================================
// Parâmetros e Sinais
// ============================================================================
parameter CLK_PERIOD = 37;          // 27 MHz -> ~37 ns
parameter BAUD_RATE = 115200;
parameter CLK_FREQ = 27_000_000;
parameter BAUD_TICKS_PER_BIT = 16;  // Oversampling 16x (padrão UART)

// Cálculo do divisor real usado pelo baud_generate interno do DUT
localparam DIVISOR = (CLK_FREQ + BAUD_RATE*8) / (BAUD_RATE*16);
// Total de ciclos de clock por bit UART
localparam CLK_CYCLES_PER_BIT = DIVISOR * BAUD_TICKS_PER_BIT;

// Sinais do DUT
reg clk_i;
reg rst_i;
reg uart_rx_drive;   // Sinal de entrada dirigido pelo testbench (quando não em loopback)
wire uart_rx_i;      // Sinal real de entrada do DUT
reg [7:0] tx_data_i;
reg tx_send_i;
wire uart_tx_o;
wire tx_ready_o;
wire [7:0] rx_data_o;
wire rx_valid_o;

// Controle de loopback
reg loopback_en;
assign uart_rx_i = loopback_en ? uart_tx_o : uart_rx_drive;

// Sinais auxiliares
integer errors = 0;
integer test_id = 0;
integer log_file;

// Gerador de baud tick externo (para verificação no TC-02)
reg baud_tick;

// Instanciação do DUT (UART completa)
uart #(
    .BAUD_RATE(BAUD_RATE),
    .CLK_FREQ(CLK_FREQ)
) dut_uart (
    .clk_i(clk_i),
    .rst_i(rst_i),
    .uart_rx_i(uart_rx_i),
    .uart_tx_o(uart_tx_o),
    .tx_data_i(tx_data_i),
    .tx_send_i(tx_send_i),
    .tx_ready_o(tx_ready_o),
    .rx_data_o(rx_data_o),
    .rx_valid_o(rx_valid_o)
);

// ============================================================================
// Geração de Clock e Reset
// ============================================================================
initial clk_i = 1'b0;
always #(CLK_PERIOD/2) clk_i = ~clk_i;

// Reset inicial
initial begin
    rst_i = 1'b0;
    uart_rx_drive = 1'b1;  // Linha em repouso
    tx_data_i = 8'h00;
    tx_send_i = 1'b0;
    loopback_en = 1'b0;
    baud_tick = 1'b0;
    #200;
    rst_i = 1'b1;
end

// ============================================================================
// Gerador de Baud Tick externo (para monitoramento no TC-02)
// ============================================================================
reg [15:0] baud_counter = 16'd0;
always @(posedge clk_i or negedge rst_i) begin
    if (!rst_i) begin
        baud_counter <= 16'd0;
        baud_tick <= 1'b0;
    end else begin
        if (baud_counter >= DIVISOR - 1) begin
            baud_counter <= 16'd0;
            baud_tick <= 1'b1;
        end else begin
            baud_counter <= baud_counter + 1'b1;
            baud_tick <= 1'b0;
        end
    end
end

// ============================================================================
// Tarefas de Suporte
// ============================================================================

// Tarefa para imprimir no console e no arquivo
task log_message;
    input string msg;
    begin
        $display("%s", msg);
        $fdisplay(log_file, "%s", msg);
    end
endtask

// Aplica reset por uma duração especificada em ciclos de clock
task apply_reset;
    input integer duration;
begin
    rst_i = 1'b0;
    repeat(duration) @(posedge clk_i);
    rst_i = 1'b1;
end
endtask

// Verifica um valor esperado contra o real (até 32 bits)
task check_value;
    input [31:0] expected;
    input [31:0] actual;
    input string description;
begin
    if (expected !== actual) begin
        log_message($sformatf("[ERRO] %s: esperado %h, obtido %h (tempo %0t)", description, expected, actual, $time));
        errors = errors + 1;
    end else begin
        log_message($sformatf("[OK]   %s (tempo %0t)", description, $time));
    end
end
endtask

// Envia um byte pelo transmissor UART usando tx_send_i e aguarda conclusão
task send_tx_byte;
    input [7:0] data;
begin
    wait(tx_ready_o == 1'b1);
    @(posedge clk_i);
    tx_data_i = data;
    tx_send_i = 1'b1;
    @(posedge clk_i);
    tx_send_i = 1'b0;
    wait(tx_ready_o == 1'b1);
end
endtask

// Recebe um byte serialmente pela entrada uart_rx_drive (gera frame UART)
// Usa ciclos de clock para garantir alinhamento com o DUT independente da fase do baud_tick
task receive_rx_byte;
    input [7:0] data;
    integer i;
begin
    // Garante linha em idle por 1 bit time
    uart_rx_drive = 1'b1;
    repeat(CLK_CYCLES_PER_BIT) @(posedge clk_i);
    // Start bit
    uart_rx_drive = 1'b0;
    repeat(CLK_CYCLES_PER_BIT) @(posedge clk_i);
    // Data bits (LSB primeiro)
    for (i = 0; i < 8; i = i + 1) begin
        uart_rx_drive = data[i];
        repeat(CLK_CYCLES_PER_BIT) @(posedge clk_i);
    end
    // Stop bit
    uart_rx_drive = 1'b1;
    repeat(CLK_CYCLES_PER_BIT) @(posedge clk_i);
end
endtask

// Aguarda rx_valid_o com timeout
task wait_rx_valid;
    input integer timeout_cycles;
    output reg success;
    integer count;
begin
    success = 0;
    count = 0;
    while (!rx_valid_o && count < timeout_cycles) begin
        @(posedge clk_i);
        count = count + 1;
    end
    if (rx_valid_o) begin
        success = 1;
    end else begin
        log_message($sformatf("[ERRO] Timeout aguardando rx_valid_o (tempo %0t)", $time));
        errors = errors + 1;
    end
end
endtask

// ============================================================================
// Casos de Teste (TC-XX)
// ============================================================================

initial begin
    // Abrir arquivo de log
    log_file = $fopen("../sim/uart_test_results.txt", "w");
    if (log_file == 0) begin
        $display("ERRO: Não foi possível criar o arquivo de log em ../sim/");
        $finish;
    end

    #200;
    log_message("=============================================");
    log_message(" Testes da UART (tx + rx integrados)");
    log_message("=============================================");

    // TC-01: Estado inicial após reset
    test_id = 1;
    log_message($sformatf("\nTC-%0d: Estado inicial após reset", test_id));
    apply_reset(5);
    check_value(1, tx_ready_o, "tx_ready_o = 1 após reset");
    check_value(1, uart_tx_o, "uart_tx_o = 1 (repouso) após reset");
    check_value(0, rx_valid_o, "rx_valid_o = 0 após reset");
    check_value(0, rx_data_o, "rx_data_o = 0 após reset");

    // TC-02: Transmissão de um byte (0xA5) e verificação do frame serial
    test_id = 2;
    log_message($sformatf("\nTC-%0d: Transmissão do byte 0xA5", test_id));
    apply_reset(3);
    fork
        begin
            send_tx_byte(8'hA5);
        end
        begin
            @(negedge uart_tx_o);
            repeat(BAUD_TICKS_PER_BIT) @(posedge baud_tick);
            if (uart_tx_o !== 1'b0) begin
                log_message($sformatf("[ERRO] Start bit: esperado 0, obtido %b (tempo %0t)", uart_tx_o, $time));
                errors = errors + 1;
            end else begin
                log_message($sformatf("[OK]   Start bit (tempo %0t)", $time));
            end

            begin
                integer i;
                reg expected_bit;
                reg [7:0] expected_byte;
                expected_byte = 8'hA5;
                for (i = 0; i < 8; i = i + 1) begin
                    repeat(BAUD_TICKS_PER_BIT) @(posedge baud_tick);
                    expected_bit = expected_byte[i];
                    if (uart_tx_o !== expected_bit) begin
                        log_message($sformatf("[ERRO] Bit de dados[%0d]: esperado %b, obtido %b (tempo %0t)", i, expected_bit, uart_tx_o, $time));
                        errors = errors + 1;
                    end else begin
                        log_message($sformatf("[OK]   Bit de dados[%0d] (tempo %0t)", i, $time));
                    end
                end
            end

            repeat(BAUD_TICKS_PER_BIT) @(posedge baud_tick);
            if (uart_tx_o !== 1'b1) begin
                log_message($sformatf("[ERRO] Stop bit: esperado 1, obtido %b (tempo %0t)", uart_tx_o, $time));
                errors = errors + 1;
            end else begin
                log_message($sformatf("[OK]   Stop bit (tempo %0t)", $time));
            end
        end
    join
    log_message("[INFO] Transmissão do byte 0xA5 concluída");

    // TC-03: Recepção de um byte (0x5A) e verificação dos dados
    test_id = 3;
    log_message($sformatf("\nTC-%0d: Recepção do byte 0x5A", test_id));
    apply_reset(3);
    fork
        begin
            receive_rx_byte(8'h5A);
        end
        begin
            reg check_ok;
            wait_rx_valid(10000, check_ok);
            if (check_ok) begin
                check_value(8'h5A, rx_data_o, "Byte recebido");
            end
        end
    join

    // TC-04: Loopback externo TX->RX (atribuição contínua)
    test_id = 4;
    log_message($sformatf("\nTC-%0d: Loopback externo TX->RX (assign)", test_id));
    apply_reset(3);

    loopback_en = 1'b1;   // ativa loopback

    send_tx_byte(8'hAA);

    begin
        reg check_ok;
        wait_rx_valid(10000, check_ok);
        if (check_ok)
            check_value(8'hAA, rx_data_o, "Byte loopback recebido");
    end

    loopback_en = 1'b0;   // desativa loopback, retorna ao drive normal
    uart_rx_drive = 1'b1; // linha em repouso

    // TC-05: Reset durante transmissão
    test_id = 5;
    log_message($sformatf("\nTC-%0d: Reset durante transmissão", test_id));
    apply_reset(3);
    fork
        begin
            send_tx_byte(8'h55);
        end
        begin
            repeat(10) @(posedge baud_tick);
            rst_i = 1'b0;
            repeat(2) @(posedge clk_i);
            rst_i = 1'b1;
        end
    join
    #100;
    check_value(1, tx_ready_o, "tx_ready_o = 1 após reset durante TX");

    // TC-06: Transmissões consecutivas (back-to-back)
    test_id = 6;
    log_message($sformatf("\nTC-%0d: Transmissões consecutivas", test_id));
    apply_reset(3);
    send_tx_byte(8'h11);
    send_tx_byte(8'h22);
    send_tx_byte(8'h33);
    log_message("[OK] Três transmissões consecutivas realizadas");

    // Resumo final
    log_message("\n=============================================");
    if (errors == 0)
        log_message("TODOS OS TESTES PASSARAM!");
    else
        log_message($sformatf("FALHAS: %0d erros encontrados", errors));
    log_message("=============================================");

    $fclose(log_file);
    $finish;
end

// ============================================================================
// Geração de VCD para visualização de ondas
// ============================================================================
initial begin
    $dumpfile("../sim/uart_tb.vcd");
    $dumpvars(0, tb_uart);
end

endmodule

cores/uart_experiments/sim/uart_tb.vcd
$date
	Tue Sep  1 13:33:56 2026
$end
$version
	Icarus Verilog
$end
$timescale
	1ps
$end
$scope module tb_uart $end
$var wire 1 ! uart_tx_o $end
$var wire 1 " uart_rx_i $end
$var wire 1 # tx_ready_o $end
$var wire 1 $ rx_valid_o $end
$var wire 8 % rx_data_o [7:0] $end
$var parameter 32 & BAUD_RATE $end
$var parameter 32 ' BAUD_TICKS_PER_BIT $end
$var parameter 97 ( CLK_CYCLES_PER_BIT $end
$var parameter 32 ) CLK_FREQ $end
$var parameter 32 * CLK_PERIOD $end
$var parameter 65 + DIVISOR $end
$var reg 16 , baud_counter [15:0] $end
$var reg 1 - baud_tick $end
$var reg 1 . clk_i $end
$var reg 1 / loopback_en $end
$var reg 1 0 rst_i $end
$var reg 8 1 tx_data_i [7:0] $end
$var reg 1 2 tx_send_i $end
$var reg 1 3 uart_rx_drive $end
$var integer 32 4 errors [31:0] $end
$var integer 32 5 log_file [31:0] $end
$var integer 32 6 test_id [31:0] $end
$scope module dut_uart $end
$var wire 1 . clk_i $end
$var wire 1 0 rst_i $end
$var wire 8 7 tx_data_i [7:0] $end
$var wire 1 2 tx_send_i $end
$var wire 1 " uart_rx_i $end
$var wire 1 ! uart_tx_o $end
$var wire 1 # tx_ready_o $end
$var wire 1 $ rx_valid_o $end
$var wire 8 8 rx_data_o [7:0] $end
$var wire 1 9 baud_tick $end
$var parameter 32 : BAUD_RATE $end
$var parameter 32 ; CLK_FREQ $end
$var parameter 1 < ENABLE_RX $end
$var parameter 1 = ENABLE_TX $end
$scope begin gen_rx $end
$scope module rx_instance $end
$var wire 1 9 baud_tick $end
$var wire 1 . clk_i $end
$var wire 1 > enable_rx $end
$var wire 1 0 rst_i $end
$var wire 1 $ rx_valid $end
$var wire 1 " uart_rx_i $end
$var parameter 2 ? DATA $end
$var parameter 2 @ IDLE $end
$var parameter 2 A START $end
$var parameter 2 B STOP $end
$var reg 2 C atual [1:0] $end
$var reg 4 D bit_count [3:0] $end
$var reg 8 E data_o [7:0] $end
$var reg 2 F proximo [1:0] $end
$var reg 1 G rs232_t $end
$var reg 1 H rs232_t1 $end
$var reg 1 I rs232_t2 $end
$var reg 4 J tick_count [3:0] $end
$upscope $end
$upscope $end
$scope begin gen_tx $end
$scope module tx_instance $end
$var wire 1 9 baud_tick $end
$var wire 1 . clk_i $end
$var wire 8 K data_i [7:0] $end
$var wire 1 2 enable_tx $end
$var wire 1 0 rst_i $end
$var wire 1 # tx_valid $end
$var parameter 2 L DATA $end
$var parameter 2 M IDLE $end
$var parameter 2 N START $end
$var parameter 2 O STOP $end
$var reg 2 P atual [1:0] $end
$var reg 4 Q bit_count [3:0] $end
$var reg 2 R proximo [1:0] $end
$var reg 4 S tick_count [3:0] $end
$var reg 8 T tx_data [7:0] $end
$var reg 1 ! uart_tx_o $end
$upscope $end
$upscope $end
$scope module baud_gen $end
$var wire 1 . clk_i $end
$var wire 1 0 rst_i $end
$var wire 1 9 baud_tick $end
$var parameter 32 U BAUD_RATE $end
$var parameter 32 V CLK_FREQ $end
$var parameter 65 W DIVISOR $end
$var reg 25 X contador_baud [24:0] $end
$upscope $end
$upscope $end
$scope begin $unm_blk_26 $end
$var reg 1 Y expected_bit $end
$var reg 8 Z expected_byte [7:0] $end
$var integer 32 [ i [31:0] $end
$upscope $end
$scope begin $unm_blk_34 $end
$var reg 1 \ check_ok $end
$upscope $end
$scope begin $unm_blk_36 $end
$var reg 1 ] check_ok $end
$upscope $end
$scope task apply_reset $end
$var integer 32 ^ duration [31:0] $end
$upscope $end
$scope task check_value $end
$var reg 32 _ actual [31:0] $end
$var reg 32 ` expected [31:0] $end
$upscope $end
$scope task log_message $end
$upscope $end
$scope task receive_rx_byte $end
$var reg 8 a data [7:0] $end
$var integer 32 b i [31:0] $end
$upscope $end
$scope task send_tx_byte $end
$var reg 8 c data [7:0] $end
$upscope $end
$scope task wait_rx_valid $end
$var reg 1 d success $end
$var integer 32 e count [31:0] $end
$var integer 32 f timeout_cycles [31:0] $end
$upscope $end
$upscope $end
$enddefinitions $end
$comment Show the parameter values. $end
$dumpall
b1111 W
b1100110111111110011000000 V
b11100001000000000 U
b11 O
b1 N
b0 M
b10 L
b11 B
b1 A
b0 @
b10 ?
1=
1<
b1100110111111110011000000 ;
b11100001000000000 :
b1111 +
b100101 *
b1100110111111110011000000 )
b11110000 (
b10000 '
b11100001000000000 &
$end
#0
$dumpvars
bx f
bx e
xd
bx c
bx b
bx a
bx `
bx _
bx ^
x]
x\
bx [
bx Z
xY
b0 X
b0 T
b0 S
b0 R
b0 Q
b0 P
b0 K
b0 J
1I
1H
1G
b0 F
b0 E
b0 D
b0 C
1>
09
b0 8
b0 7
b0 6
b10000000000000000000000000000011 5
b0 4
13
02
b0 1
00
0/
0.
0-
b0 ,
b0 %
0$
1#
1"
1!
$end
#18000
1.
#36000
0.
#54000
1.
#72000
0.
#90000
1.
#108000
0.
#126000
1.
#144000
0.
#162000
1.
#180000
0.
#198000
1.
#200000
b101 ^
b1 6
00
#216000
0.
#234000
1.
#252000
0.
#270000
1.
#288000
0.
#306000
1.
#324000
0.
#342000
1.
#360000
0.
#378000
b11 ^
b10 6
b0 _
b0 `
00
1.
#396000
0.
#414000
1.
#432000
0.
#450000
1.
#468000
0.
#486000
b1 ,
b1 X
b10100101 c
10
1.
#504000
0.
#522000
b10100101 T
b10 X
b10 ,
b1 R
12
b10100101 1
b10100101 7
b10100101 K
1.
#540000
0.
#558000
b11 ,
b11 X
0#
b1 P
b1 R
02
1.
#576000
0.
#594000
0!
b100 X
b100 ,
1.
#612000
0.
#630000
b101 ,
b101 X
1.
#648000
0.
#666000
b110 X
b110 ,
1.
#684000
0.
#702000
b111 ,
b111 X
1.
#720000
0.
#738000
b1000 X
b1000 ,
1.
#756000
0.
#774000
b1001 ,
b1001 X
1.
#792000
0.
#810000
b1010 X
b1010 ,
1.
#828000
0.
#846000
b1011 ,
b1011 X
1.
#864000
0.
#882000
b1100 X
b1100 ,
1.
#900000
0.
#918000
b1101 ,
b1101 X
1.
#936000
0.
#954000
19
b1110 X
b1110 ,
1.
#972000
0.
#990000
09
1-
b0 ,
b0 X
b1 S
1.
#1008000
0.
#1026000
b1 X
0-
b1 ,
1.
#1044000
0.
#1062000
b10 ,
b10 X
1.
#1080000
0.
#1098000
b11 X
b11 ,
1.
#1116000
0.
#1134000
b100 ,
b100 X
1.
#1152000
0.
#1170000
b101 X
b101 ,
1.
#1188000
0.
#1206000
b110 ,
b110 X
1.
#1224000
0.
#1242000
b111 X
b111 ,
1.
#1260000
0.
#1278000
b1000 ,
b1000 X
1.
#1296000
0.
#1314000
b1001 X
b1001 ,
1.
#1332000
0.
#1350000
b1010 ,
b1010 X
1.
#1368000
0.
#1386000
b1011 X
b1011 ,
1.
#1404000
0.
#1422000
b1100 ,
b1100 X
1.
#1440000
0.
#1458000
b1101 X
b1101 ,
1.
#1476000
0.
#1494000
19
b1110 ,
b1110 X
1.
#1512000
0.
#1530000
09
b10 S
b0 X
1-
b0 ,
1.
#1548000
0.
#1566000
0-
b1 ,
b1 X
1.
#1584000
0.
#1602000
b10 X
b10 ,
1.
#1620000
0.
#1638000
b11 ,
b11 X
1.
#1656000
0.
#1674000
b100 X
b100 ,
1.
#1692000
0.
#1710000
b101 ,
b101 X
1.
#1728000
0.
#1746000
b110 X
b110 ,
1.
#1764000
0.
#1782000
b111 ,
b111 X
1.
#1800000
0.
#1818000
b1000 X
b1000 ,
1.
#1836000
0.
#1854000
b1001 ,
b1001 X
1.
#1872000
0.
#1890000
b1010 X
b1010 ,
1.
#1908000
0.
#1926000
b1011 ,
b1011 X
1.
#1944000
0.
#1962000
b1100 X
b1100 ,
1.
#1980000
0.
#1998000
b1101 ,
b1101 X
1.
#2016000
0.
#2034000
19
b1110 X
b1110 ,
1.
#2052000
0.
#2070000
09
1-
b0 ,
b0 X
b11 S
1.
#2088000
0.
#2106000
b1 X
0-
b1 ,
1.
#2124000
0.
#2142000
b10 ,
b10 X
1.
#2160000
0.
#2178000
b11 X
b11 ,
1.
#2196000
0.
#2214000
b100 ,
b100 X
1.
#2232000
0.
#2250000
b101 X
b101 ,
1.
#2268000
0.
#2286000
b110 ,
b110 X
1.
#2304000
0.
#2322000
b111 X
b111 ,
1.
#2340000
0.
#2358000
b1000 ,
b1000 X
1.
#2376000
0.
#2394000
b1001 X
b1001 ,
1.
#2412000
0.
#2430000
b1010 ,
b1010 X
1.
#2448000
0.
#2466000
b1011 X
b1011 ,
1.
#2484000
0.
#2502000
b1100 ,
b1100 X
1.
#2520000
0.
#2538000
b1101 X
b1101 ,
1.
#2556000
0.
#2574000
19
b1110 ,
b1110 X
1.
#2592000
0.
#2610000
09
b100 S
b0 X
1-
b0 ,
1.
#2628000
0.
#2646000
0-
b1 ,
b1 X
1.
#2664000
0.
#2682000
b10 X
b10 ,
1.
#2700000
0.
#2718000
b11 ,
b11 X
1.
#2736000
0.
#2754000
b100 X
b100 ,
1.
#2772000
0.
#2790000
b101 ,
b101 X
1.
#2808000
0.
#2826000
b110 X
b110 ,
1.
#2844000
0.
#2862000
b111 ,
b111 X
1.
#2880000
0.
#2898000
b1000 X
b1000 ,
1.
#2916000
0.
