systems/tangnano20k_uart/final/baud_generate.v
module baud_generate #(
    parameter BAUD_RATE = 115200,     
    parameter CLK_FREQ = 27_000_000    
) (
    input wire clk_i,
    input wire rst_i,
    
    output wire baud_tick
);

    // Calcula o divisor para 16x Oversampling com ARREDONDAMENTO:
    // A soma de "(BAUD_RATE * 8)" equivale a somar 0.5 antes de dividir.
    // Assim, 14.64 vira 15.14, e ao truncar, o Verilog crava no 15 correto!
    
    localparam DIVISOR = (CLK_FREQ + (BAUD_RATE * 8)) / (BAUD_RATE * 16);
    
    reg [24:0] contador_baud;
    
    always @(posedge clk_i or negedge rst_i) begin
        if (!rst_i) begin
            contador_baud <= 25'b0;
        end
        else if (contador_baud >= DIVISOR - 1) begin
            contador_baud <= 25'b0;
        end
        else begin
            contador_baud <= contador_baud + 1'b1;
        end
    end
    
    // Gera um pulso (baud_tick) a cada DIVISOR clocks (16 pulsos formam 1 bit)
    assign baud_tick = (contador_baud == DIVISOR - 1) ? 1'b1 : 1'b0;

endmodule

cores/uart_experiments/tb/tb_baud_generate.v
`timescale 1ns/1ps

module tb_baud_generate();
    reg clk_i = 0;
    reg rst_i = 0;
    wire baud_tick;

    // Contadores de automação
    integer success_count = 0;
    integer fail_count = 0;
    reg [31:0] cycle_counter = 0;
    reg first_tick_seen = 0;
    
    // Arquivo de log
    integer log_file;

    // Geração do clock principal (27MHz -> Período de ~37.03ns)
    always #18.5 clk_i = ~clk_i;

    // Instanciação do Device Under Test (DUT)
    baud_generate #(
        .BAUD_RATE(115200),
        .CLK_FREQ(27_000_000)
    ) dut (
        .clk_i(clk_i),
        .rst_i(rst_i),
        .baud_tick(baud_tick)
    );

    // Tarefa para imprimir no console e no arquivo
    task log_message;
        input string msg;
        begin
            $display("%s", msg);
            $fdisplay(log_file, "%s", msg);
        end
    endtask

    // BLOCO AUTOMATIZADO DE VALIDAÇÃO
    always @(posedge clk_i or negedge rst_i) begin
        if (!rst_i) begin
            cycle_counter <= 0;
            first_tick_seen <= 0;
        end else begin
            if (baud_tick) begin
                if (!first_tick_seen) begin
                    first_tick_seen <= 1'b1;
                    cycle_counter <= 0;
                end else begin
                    if (cycle_counter == 14) begin
                        success_count <= success_count + 1;
                        log_message("[SUCCESS] Tick recebido no tempo exato (15 ciclos).");
                    end else begin
                        fail_count <= fail_count + 1;
                        log_message($sformatf("[FAIL] Tick fora de hora! Intervalo medido: %0d ciclos (Esperado: 15)", cycle_counter));
                    end
                    cycle_counter <= 0;
                end
            end else begin
                cycle_counter <= cycle_counter + 1'b1;
            end
        end
    end

    // CENÁRIOS DE TESTE
    initial begin
        // Abrir arquivo de log (pasta sim irmã de tb)
        log_file = $fopen("../sim/baud_generate_test_results.txt", "w");
        if (log_file == 0) begin
            $display("ERRO: Não foi possível criar o arquivo de log.");
            $finish;
        end

        log_message("==================================================");
        log_message("   INICIO DA AUTOMACAO: tb_baud_generate          ");
        log_message("==================================================");
        
        rst_i = 1'b0;
        #200;
        rst_i = 1'b1;
        
        #20000;
        
        log_message("==================================================");
        log_message("   RELATORIO FINAL DE TESTES                      ");
        log_message("==================================================");
        log_message($sformatf(" TOTAL DE SUCCESS : %0d", success_count));
        log_message($sformatf(" TOTAL DE FAILS   : %0d", fail_count));
        log_message("==================================================");
        
        if (fail_count == 0 && success_count > 0) begin
            log_message(" RESULTADO: APROVADO COM SUCESSO!");
        end else begin
            log_message(" RESULTADO: REPROVADO!");
        end
        log_message("==================================================");
        
        $fclose(log_file);
        $finish;
    end

    // Dump para waveform
    initial begin
        $dumpfile("../sim/baud_generate_tb.vcd");
        $dumpvars(0, tb_baud_generate);
    end
endmodule

cores/baud_generate/sim/baud_generate_tb.vcd
$date
	Sun Aug 30 09:22:46 2026
$end
$version
	Icarus Verilog
$end
$timescale
	1ps
$end
$scope module tb_baud_generate $end
$var wire 1 ! baud_tick $end
$var reg 1 " clk_i $end
$var reg 32 # cycle_counter [31:0] $end
$var reg 1 $ first_tick_seen $end
$var reg 1 % rst_i $end
$var integer 32 & fail_count [31:0] $end
$var integer 32 ' log_file [31:0] $end
$var integer 32 ( success_count [31:0] $end
$scope module dut $end
$var wire 1 " clk_i $end
$var wire 1 % rst_i $end
$var wire 1 ! baud_tick $end
$var parameter 32 ) BAUD_RATE $end
$var parameter 32 * CLK_FREQ $end
$var parameter 65 + DIVISOR $end
$var reg 25 , contador_baud [24:0] $end
$upscope $end
$scope task log_message $end
$upscope $end
$upscope $end
$enddefinitions $end
$comment Show the parameter values. $end
$dumpall
b1111 +
b1100110111111110011000000 *
b11100001000000000 )
$end
#0
$dumpvars
bx ,
b0 (
b10000000000000000000000000000011 '
b0 &
0%
0$
b0 #
0"
x!
$end
#18500
0!
b0 ,
1"
#37000
0"
#55500
1"
#74000
0"
#92500
1"
#111000
0"
#129500
1"
#148000
0"
#166500
1"
#185000
0"
#200000
1%
#203500
b1 #
b1 ,
1"
#222000
0"
#240500
b10 ,
b10 #
1"
#259000
0"
#277500
b11 #
b11 ,
1"
#296000
0"
#314500
b100 ,
b100 #
1"
#333000
0"
#351500
b101 #
b101 ,
1"
#370000
0"
#388500
b110 ,
b110 #
1"
#407000
0"
#425500
b111 #
b111 ,
1"
#444000
0"
#462500
b1000 ,
b1000 #
1"
#481000
0"
#499500
b1001 #
b1001 ,
1"
#518000
0"
#536500
b1010 ,
b1010 #
1"
#555000
0"
#573500
b1011 #
b1011 ,
1"
#592000
0"
#610500
b1100 ,
b1100 #
1"
#629000
0"
#647500
b1101 #
b1101 ,
1"
#666000
0"
#684500
1!
b1110 ,
b1110 #
1"
#703000
0"
#721500
0!
b0 #
1$
b0 ,
1"
#740000
0"
#758500
b1 ,
b1 #
1"
#777000
0"
#795500
b10 #
b10 ,
1"
#814000
0"
#832500
b11 ,
b11 #
1"
#851000
0"
#869500
b100 #
b100 ,
1"
#888000
0"
#906500
b101 ,
b101 #
1"
#925000
0"
#943500
b110 #
b110 ,
1"
#962000
0"
#980500
b111 ,
b111 #
1"
#999000
0"
#1017500
b1000 #
b1000 ,
1"
#1036000
0"
#1054500
b1001 ,
b1001 #
1"
#1073000
0"
#1091500
b1010 #
b1010 ,
1"
#1110000
0"
#1128500
b1011 ,
b1011 #
1"
#1147000
0"
#1165500
b1100 #
b1100 ,
1"
#1184000
0"
#1202500
b1101 ,
b1101 #
1"
#1221000
0"
#1239500
1!
b1110 #
b1110 ,
1"
#1258000
0"
#1276500
0!
b0 #
b0 ,
b1 (
1"
#1295000
0"
#1313500
b1 ,
b1 #
1"
#1332000
0"
#1350500
b10 #
b10 ,
1"
#1369000
0"
#1387500
b11 ,
b11 #
1"
#1406000
0"
#1424500
b100 #
b100 ,
1"
#1443000
0"
#1461500
b101 ,
b101 #
1"
#1480000
0"
#1498500
b110 #
b110 ,
1"
#1517000
0"
#1535500
b111 ,
b111 #
1"
#1554000
0"
#1572500
b1000 #
b1000 ,
1"
#1591000
0"
#1609500
b1001 ,
b1001 #
1"
#1628000
0"
#1646500
b1010 #
b1010 ,
1"
#1665000
0"
#1683500
b1011 ,
b1011 #
1"
#1702000
0"
#1720500
b1100 #
b1100 ,
1"
#1739000
0"
#1757500
b1101 ,
b1101 #
1"
#1776000
0"
#1794500
1!
b1110 #
b1110 ,
1"
#1813000
0"
#1831500
0!
b0 #
b0 ,
b10 (
1"
#1850000
0"
#1868500
b1 ,
b1 #
1"
#1887000
0"
#1905500
b10 #
b10 ,
1"
#1924000
0"
#1942500
b11 ,
b11 #
1"
#1961000
0"
#1979500
b100 #
b100 ,
1"
#1998000
0"
#2016500
b101 ,
b101 #
1"
#2035000
0"
#2053500
b110 #
b110 ,
1"
#2072000
0"
#2090500
b111 ,
b111 #
1"
#2109000
0"
#2127500
b1000 #
b1000 ,
1"
#2146000
0"
#2164500
b1001 ,
b1001 #
1"
#2183000
0"
#2201500
b1010 #
b1010 ,
1"
#2220000
0"
#2238500
b1011 ,
b1011 #
1"
#2257000
0"
#2275500
b1100 #
b1100 ,
1"
#2294000
0"
#2312500
b1101 ,
b1101 #
1"
#2331000
0"
#2349500
1!
b1110 #
b1110 ,
1"
#2368000
0"
#2386500
0!
b0 #
b0 ,
b11 (
1"
#2405000
0"
#2423500
b1 ,
b1 #
1"
#2442000
0"
#2460500
b10 #
b10 ,
1"
#2479000
0"
#2497500
b11 ,
b11 #
1"
#2516000
0"
#2534500
b100 #
b100 ,
1"
#2553000
0"
#2571500
b101 ,
b101 #
1"
#2590000
0"
#2608500
b110 #
b110 ,
1"
#2627000
0"
#2645500
b111 ,
b111 #
1"
#2664000
0"
#2682500
b1000 #
b1000 ,
1"
#2701000
0"
#2719500
b1001 ,
b1001 #
1"
#2738000
0"
#2756500
b1010 #
b1010 ,
1"
#2775000
0"
#2793500
b1011 ,
b1011 #
1"
#2812000
0"
#2830500
b1100 #
b1100 ,
1"
#2849000
0"
#2867500
b1101 ,
b1101 #
1"
#2886000
0"
#2904500
1!
b1110 #
b1110 ,
1"
#2923000
0"
#2941500
0!
b0 #
b0 ,
b100 (
1"
#2960000
0"
#2978500
b1 ,
b1 #
1"
#2997000
0"
#3015500
b10 #
b10 ,
1"
#3034000
0"
#3052500
b11 ,
b11 #
1"
#3071000
0"
#3089500
b100 #
b100 ,
1"
#3108000
0"
#3126500
b101 ,
b101 #
1"
#3145000
0"
#3163500
b110 #
b110 ,
1"
#3182000
0"
#3200500
b111 ,
b111 #
1"
#3219000
0"
#3237500
b1000 #
b1000 ,
1"
#3256000
0"
#3274500
b1001 ,
b1001 #
1"
#3293000
0"
#3311500
b1010 #
b1010 ,
1"
#3330000
0"
#3348500
b1011 ,
b1011 #
1"
#3367000
0"
#3385500
b1100 #
b1100 ,
1"
#3404000
0"
#3422500
b1101 ,
b1101 #
1"
#3441000
0"
#3459500
1!
b1110 #
b1110 ,
1"
#3478000
0"
#3496500
0!
b0 #
b0 ,
b101 (
1"
#3515000
0"
#3533500
b1 ,
b1 #
1"
#3552000
0"
#3570500
b10 #
b10 ,
1"
#3589000
0"
#3607500
b11 ,
b11 #
1"
#3626000
0"
#3644500
b100 #
b100 ,
1"
#3663000
0"
#3681500
b101 ,
b101 #
1"
#3700000
0"
#3718500
b110 #
b110 ,
1"
#3737000
0"
#3755500
b111 ,
b111 #
1"
#3774000
0"
#3792500
b1000 #
b1000 ,
1"
#3811000
0"
#3829500
b1001 ,
b1001 #
1"
#3848000
0"
#3866500
b1010 #
b1010 ,
1"
#3885000
0"
#3903500
b1011 ,
b1011 #
1"
#3922000
0"
#3940500
b1100 #
b1100 ,
1"
#3959000
0"
#3977500
b1101 ,
b1101 #
1"
#3996000
0"
#4014500
1!
b1110 #
b1110 ,
1"
#4033000
0"
#4051500
0!
b0 #
b0 ,
b110 (
1"
#4070000
0"
#4088500
b1 ,
b1 #
1"
#4107000
0"
#4125500
b10 #
b10 ,
1"
#4144000
0"
#4162500
b11 ,
b11 #
1"
#4181000
0"
#4199500
b100 #
b100 ,
1"
#4218000
0"
#4236500
b101 ,
b101 #
1"
#4255000
0"
#4273500
b110 #
b110 ,
1"
#4292000
0"
#4310500
b111 ,
b111 #
1"
#4329000
0"
#4347500
b1000 #
b1000 ,
1"
#4366000
0"
#4384500
b1001 ,
b1001 #
1"
#4403000
0"
#4421500
b1010 #
b1010 ,
1"
#4440000
0"
#4458500
b1011 ,
b1011 #
1"
#4477000
0"
#4495500
b1100 #
b1100 ,
1"
#4514000
0"
#4532500
b1101 ,
b1101 #
1"
#4551000
0"
#4569500
1!
b1110 #
b1110 ,
1"
#4588000
0"
#4606500
0!
b0 #
b0 ,
b111 (
1"
#4625000
0"
#4643500
b1 ,
b1 #
1"
#4662000
0"
#4680500
b10 #
b10 ,
1"
#4699000
0"
#4717500
b11 ,
b11 #
1"
#4736000
0"
#4754500
b100 #
b100 ,
1"
#4773000
0"
#4791500
b101 ,
b101 #
1"
#4810000
0"
#4828500
b110 #
b110 ,
1"
#4847000
0"
#4865500
b111 ,
b111 #
1"
#4884000
0"
#4902500
b1000 #
b1000 ,
1"
#4921000
0"
#4939500
b1001 ,
b1001 #
1"
#4958000
0"
#4976500
b1010 #
b1010 ,
1"
#4995000
0"
#5013500
b1011 ,
b1011 #
1"
#5032000
0"
#5050500
b1100 #
b1100 ,
1"
#5069000
0"
#5087500
b1101 ,
b1101 #
1"
#5106000
0"
#5124500
1!
b1110 #
b1110 ,
1"
#5143000
0"
#5161500
0!
b0 #
b0 ,
b1000 (
1"
#5180000
0"
#5198500
b1 ,
b1 #
1"
#5217000
0"
#5235500
b10 #
b10 ,
1"
#5254000
0"
#5272500
b11 ,
b11 #
1"
#5291000
0"
#5309500
b100 #
b100 ,
1"
#5328000
0"
#5346500
b101 ,
b101 #
1"
#5365000
0"
#5383500
b110 #
b110 ,
1"
#5402000
0"
#5420500
b111 ,
b111 #
1"
#5439000
0"
#5457500
b1000 #
b1000 ,
1"
#5476000
0"
#5494500
b1001 ,
b1001 #
1"
#5513000
0"
#5531500
b1010 #
b1010 ,
1"
#5550000
0"
#5568500
b1011 ,
b1011 #
1"
#5587000
0"
#5605500
b1100 #
b1100 ,
1"
#5624000
0"
#5642500
b1101 ,
b1101 #
1"
#5661000
0"
#5679500
1!
b1110 #
b1110 ,
1"
#5698000
0"
#5716500
0!
b0 #
b0 ,
b1001 (
1"
#5735000
0"
#5753500
b1 ,
b1 #
1"
#5772000
0"
#5790500
b10 #
b10 ,
1"
#5809000
0"
#5827500
b11 ,
b11 #
1"
#5846000
0"
#5864500
b100 #
b100 ,
1"
#5883000
0"
#5901500
b101 ,
b101 #
1"
#5920000
0"
#5938500
b110 #
b110 ,
1"
#5957000
0"
#5975500
b111 ,
b111 #
1"
#5994000
0"
#6012500
b1000 #
b1000 ,
1"
#6031000
0"
#6049500
b1001 ,
b1001 #
1"
#6068000
0"
#6086500
b1010 #
b1010 ,
1"
#6105000
0"
#6123500
b1011 ,
b1011 #
1"
#6142000
0"
#6160500
b1100 #
b1100 ,
1"
#6179000
0"
#6197500
b1101 ,
b1101 #
1"
#6216000
0"
#6234500
1!
b1110 #
b1110 ,
1"
#6253000
0"
#6271500
0!
b0 #
b0 ,
b1010 (
1"
#6290000
0"
#6308500
b1 ,
b1 #
1"
#6327000
0"
#6345500
b10 #
b10 ,
1"
#6364000
0"
#6382500
b11 ,
b11 #
1"
#6401000
0"
#6419500
b100 #
b100 ,
1"
#6438000
0"
#6456500
b101 ,
b101 #
1"
#6475000
0"
#6493500
b110 #
b110 ,
1"
#6512000
0"
#6530500
b111 ,
b111 #
1"
#6549000
0"
#6567500
b1000 #
b1000 ,
1"
#6586000
0"
#6604500
b1001 ,
b1001 #
1"
#6623000
0"
#6641500
b1010 #
b1010 ,
1"
#6660000
0"
#6678500
b1011 ,
b1011 #
1"
#6697000
0"
#6715500
b1100 #
b1100 ,
1"
#6734000
0"
#6752500
b1101 ,
b1101 #
1"
#6771000
0"
#6789500
1!
b1110 #
b1110 ,
1"
#6808000
0"
#6826500
0!
b0 #
b0 ,
b1011 (
1"
#6845000
0"
#6863500
b1 ,
b1 #
1"
#6882000
0"
#6900500
b10 #
b10 ,
1"
#6919000
0"
#6937500
b11 ,
b11 #
1"
#6956000
0"
#6974500
b100 #
b100 ,
1"
#6993000
0"
#7011500
b101 ,
b101 #
1"
#7030000
0"
#7048500
b110 #
b110 ,
1"
#7067000
0"
#7085500
b111 ,
b111 #
1"
#7104000
0"
#7122500
b1000 #
b1000 ,
1"
#7141000
0"
#7159500
b1001 ,
b1001 #
1"
#7178000
0"
#7196500
b1010 #
b1010 ,
1"
#7215000
0"
#7233500
b1011 ,
b1011 #
1"
#7252000
0"
#7270500
b1100 #
b1100 ,
1"
#7289000
0"
#7307500
b1101 ,
b1101 #
1"
#7326000
0"
#7344500
1!
b1110 #
b1110 ,
1"
#7363000
0"
#7381500
0!
b0 #
b0 ,
b1100 (
1"
#7400000
0"
#7418500
b1 ,
b1 #
1"
#7437000
0"
#7455500
b10 #
b10 ,
1"
#7474000
0"
#7492500
b11 ,
b11 #
1"
#7511000
0"
#7529500
b100 #
b100 ,
1"
#7548000
0"
#7566500
b101 ,
b101 #
1"
#7585000
0"
#7603500
b110 #
b110 ,
1"
#7622000
0"
#7640500
b111 ,
b111 #
1"
#7659000
0"
#7677500
b1000 #
b1000 ,
1"
#7696000
0"
#7714500
b1001 ,
b1001 #
1"
#7733000
0"
#7751500
b1010 #
b1010 ,
1"
#7770000
0"
#7788500
b1011 ,
b1011 #
1"
#7807000
0"
#7825500
b1100 #
b1100 ,
1"
#7844000
0"
#7862500
b1101 ,
b1101 #
1"
#7881000
0"
#7899500
1!
b1110 #
b1110 ,
1"
#7918000
0"
#7936500
0!
b0 #
b0 ,
b1101 (
1"
#7955000
0"
#7973500
b1 ,
b1 #
1"
#7992000
0"
#8010500
b10 #
b10 ,
1"
#8029000
0"
#8047500
b11 ,
b11 #
1"
#8066000
0"
#8084500
b100 #
b100 ,
1"
#8103000
0"
#8121500
b101 ,
b101 #
1"
#8140000
0"
#8158500
b110 #
b110 ,
1"
#8177000
0"
#8195500
b111 ,
b111 #
1"
#8214000
0"
#8232500
b1000 #
b1000 ,
1"
#8251000
0"
#8269500
b1001 ,
b1001 #
1"
#8288000
0"
#8306500
b1010 #
b1010 ,
1"
#8325000
0"
#8343500
b1011 ,
b1011 #
1"
#8362000
0"
#8380500
b1100 #
b1100 ,
1"
#8399000
0"
#8417500
b1101 ,
b1101 #
1"
#8436000
0"
#8454500
1!
b1110 #
b1110 ,
1"
#8473000
0"
#8491500
0!
b0 #
b0 ,
b1110 (
1"
#8510000
0"
#8528500
b1 ,
b1 #
1"
#8547000
0"
#8565500
b10 #
b10 ,
1"
#8584000
0"
#8602500
b11 ,
b11 #
1"
#8621000
0"
#8639500
b100 #
b100 ,
1"
#8658000
0"
#8676500
b101 ,
b101 #
1"
#8695000
0"
#8713500
b110 #
b110 ,
1"
#8732000
0"
#8750500
b111 ,
b111 #
1"
#8769000
0"
#8787500
b1000 #
b1000 ,
1"
#8806000
0"
#8824500
b1001 ,
b1001 #
1"
#8843000
0"
#8861500
b1010 #
b1010 ,
1"
#8880000
0"
#8898500
b1011 ,
b1011 #
1"
#8917000
0"
#8935500
b1100 #
b1100 ,
1"
#8954000
0"
#8972500
b1101 ,
b1101 #
1"
#8991000
0"
#9009500
1!
b1110 #
b1110 ,
1"
#9028000
0"
#9046500
0!
b0 #
b0 ,
b1111 (
1"
#9065000
0"
#9083500
b1 ,
b1 #
1"
#9102000
0"
#9120500
b10 #
b10 ,
1"
#9139000
0"
#9157500
b11 ,
b11 #
1"
#9176000
0"
#9194500
b100 #
b100 ,
1"
#9213000
0"
#9231500
b101 ,
b101 #
1"
#9250000
0"
#9268500
b110 #
b110 ,
1"
#9287000
0"
#9305500
b111 ,
b111 #
1"
#9324000
0"
#9342500
b1000 #
b1000 ,
1"
#9361000
0"
#9379500
b1001 ,
b1001 #
1"
#9398000
0"
#9416500
b1010 #
b1010 ,
1"
#9435000
0"
#9453500
b1011 ,
b1011 #
1"
#9472000
0"
#9490500
b1100 #
b1100 ,
1"
#9509000
0"
#9527500
b1101 ,
b1101 #
1"
#9546000
0"
#9564500
1!
b1110 #
b1110 ,
1"
#9583000
0"
#9601500
0!
b0 #
b0 ,
b10000 (
1"
#9620000
0"
#9638500
b1 ,
b1 #
1"
#9657000
0"
#9675500
b10 #
b10 ,
1"
#9694000
0"
#9712500
b11 ,
b11 #
1"
#9731000
0"
#9749500
b100 #
b100 ,
1"
#9768000
0"
#9786500
b101 ,
b101 #
1"
#9805000
0"
#9823500
b110 #
b110 ,
1"
#9842000
0"
#9860500
b111 ,
b111 #
1"
#9879000
0"
#9897500
b1000 #
b1000 ,
1"
#9916000
0"
#9934500
b1001 ,
b1001 #
1"
#9953000
0"
#9971500
b1010 #
b1010 ,
1"
#9990000
0"
#10008500
b1011 ,
b1011 #
1"
#10027000
0"
#10045500
b1100 #
b1100 ,
1"
#10064000
0"
#10082500
b1101 ,
b1101 #
1"
#10101000
0"
#10119500
1!
b1110 #
b1110 ,
1"
#10138000
0"
#10156500
0!
b0 #
b0 ,
b10001 (
1"
#10175000
0"
#10193500
b1 ,
b1 #
1"
#10212000
0"
#10230500
b10 #
b10 ,
1"
#10249000
0"
#10267500
b11 ,
b11 #
1"
#10286000
0"
#10304500
b100 #
b100 ,
1"
#10323000
0"
#10341500
b101 ,
b101 #
1"
#10360000
0"
#10378500
b110 #
b110 ,
1"
#10397000
0"
#10415500
b111 ,
b111 #
1"
#10434000
0"
#10452500
b1000 #
b1000 ,
1"
#10471000
0"
#10489500
b1001 ,
b1001 #
1"
#10508000
0"
#10526500
b1010 #
b1010 ,
1"
#10545000
0"
#10563500
b1011 ,
b1011 #
1"
#10582000
0"
#10600500
b1100 #
b1100 ,
1"
#10619000
0"
#10637500
b1101 ,
b1101 #
1"
#10656000
0"
#10674500
1!
b1110 #
b1110 ,
1"
#10693000
0"
#10711500
0!
b0 #
b0 ,
b10010 (
1"
#10730000
0"
#10748500
b1 ,
b1 #
1"
#10767000
0"
#10785500
b10 #
b10 ,
1"
#10804000
0"
#10822500
b11 ,
b11 #
1"
#10841000
0"
#10859500
b100 #
b100 ,
1"
#10878000
0"
#10896500
b101 ,
b101 #
1"
#10915000
0"
#10933500
b110 #
b110 ,
1"
#10952000
0"
#10970500
b111 ,
b111 #
1"
#10989000
0"
#11007500
b1000 #
b1000 ,
1"
#11026000
0"
#11044500
b1001 ,
b1001 #
1"
#11063000
0"
#11081500
b1010 #
b1010 ,
1"
#11100000
0"
#11118500
b1011 ,
b1011 #
1"
#11137000
0"
#11155500
b1100 #
b1100 ,
1"
#11174000
0"
#11192500
b1101 ,
b1101 #
1"
#11211000
0"
#11229500
1!
b1110 #
b1110 ,
1"
#11248000
0"
#11266500
0!
b0 #
b0 ,
b10011 (
1"
#11285000
0"
#11303500
b1 ,
b1 #
1"
#11322000
0"
#11340500
b10 #
b10 ,
1"
#11359000
0"
#11377500
b11 ,
b11 #
1"
#11396000
0"
#11414500
b100 #
b100 ,
1"
#11433000
0"
#11451500
b101 ,
b101 #
1"
#11470000
0"
#11488500
b110 #
b110 ,
1"
#11507000
0"
#11525500
b111 ,
b111 #
1"
#11544000
0"
#11562500
b1000 #
b1000 ,
1"
#11581000
0"
#11599500
b1001 ,
b1001 #
1"
#11618000
0"
#11636500
b1010 #
b1010 ,
1"
#11655000
0"
#11673500
b1011 ,
b1011 #
1"
#11692000
0"
#11710500
b1100 #
b1100 ,
1"
#11729000
0"
#11747500
b1101 ,
b1101 #
1"
#11766000
0"
#11784500
1!
b1110 #
b1110 ,
1"
#11803000
0"
#11821500
0!
b0 #
b0 ,
b10100 (
1"
#11840000
0"
#11858500
b1 ,
b1 #
1"
#11877000
0"
#11895500
b10 #
b10 ,
1"
#11914000
0"
#11932500
b11 ,
b11 #
1"
#11951000
0"
#11969500
b100 #
b100 ,
1"
#11988000
0"
#12006500
b101 ,
b101 #
1"
#12025000
0"
#12043500
b110 #
b110 ,
1"
#12062000
0"
#12080500
b111 ,
b111 #
1"
#12099000
0"
#12117500
b1000 #
b1000 ,
1"
#12136000
0"
#12154500
b1001 ,
b1001 #
1"
#12173000
0"
#12191500
b1010 #
b1010 ,
1"
#12210000
0"
#12228500
b1011 ,
b1011 #
1"
#12247000
0"
#12265500
b1100 #
b1100 ,
1"
#12284000
0"
#12302500
b1101 ,
b1101 #
1"
#12321000
0"
#12339500
1!
b1110 #
b1110 ,
1"
#12358000
0"
#12376500
0!
b0 #
b0 ,
b10101 (
1"
#12395000
0"
#12413500
b1 ,
b1 #
1"
#12432000
0"
#12450500
b10 #
b10 ,
1"
#12469000
0"
#12487500
b11 ,
b11 #
1"
#12506000
0"
#12524500
b100 #
b100 ,
1"
#12543000
0"
#12561500
b101 ,
b101 #
1"
#12580000
0"
#12598500
b110 #
b110 ,
1"
#12617000
0"
#12635500
b111 ,
b111 #
1"
#12654000
0"
#12672500
b1000 #
b1000 ,
1"
#12691000
0"
#12709500
b1001 ,
b1001 #
1"
#12728000
0"
#12746500
b1010 #
b1010 ,
1"
#12765000
0"
#12783500
b1011 ,
b1011 #
1"
#12802000
0"
#12820500
b1100 #
b1100 ,
1"
#12839000
0"
#12857500
b1101 ,
b1101 #
1"
#12876000
0"
#12894500
1!
b1110 #
b1110 ,
1"
#12913000
0"
#12931500
0!
b0 #
b0 ,
b10110 (
1"
#12950000
0"
#12968500
b1 ,
b1 #
1"
#12987000
0"
#13005500
b10 #
b10 ,
1"
#13024000
0"
#13042500
b11 ,
b11 #
1"
#13061000
0"
#13079500
b100 #
b100 ,
1"
#13098000
0"
#13116500
b101 ,
b101 #
1"
#13135000
0"
#13153500
b110 #
b110 ,
1"
#13172000
0"
#13190500
b111 ,
b111 #
1"
#13209000
0"
#13227500
b1000 #
b1000 ,
1"
#13246000
0"
#13264500
b1001 ,
b1001 #
1"
#13283000
0"
#13301500
b1010 #
b1010 ,
1"
#13320000
0"
#13338500
b1011 ,
b1011 #
1"
#13357000
0"
#13375500
b1100 #
b1100 ,
1"
#13394000
0"
#13412500
b1101 ,
b1101 #
1"
#13431000
0"
#13449500
1!
b1110 #
b1110 ,
1"
#13468000
0"
#13486500
0!
b0 #
b0 ,
b10111 (
1"
#13505000
0"
#13523500
b1 ,
b1 #
1"
#13542000
0"
#13560500
b10 #
b10 ,
1"
#13579000
0"
#13597500
b11 ,
b11 #
1"
#13616000
0"
#13634500
b100 #
b100 ,
1"
#13653000
0"
#13671500
b101 ,
b101 #
1"
#13690000
0"
#13708500
b110 #
b110 ,
1"
#13727000
0"
#13745500
b111 ,
b111 #
1"
#13764000
0"
#13782500
b1000 #
b1000 ,
1"
#13801000
0"
#13819500
b1001 ,
b1001 #
1"
#13838000
0"
#13856500
b1010 #
b1010 ,
1"
#13875000
0"
#13893500
b1011 ,
b1011 #
1"
#13912000
0"
#13930500
b1100 #
b1100 ,
1"
#13949000
0"
#13967500
b1101 ,
b1101 #
1"
#13986000
0"
#14004500
1!
b1110 #
b1110 ,
1"
#14023000
0"
#14041500
0!
b0 #
b0 ,
b11000 (
1"
#14060000
0"
#14078500
b1 ,
b1 #
1"
#14097000
0"
#14115500
b10 #
b10 ,
1"
#14134000
0"
#14152500
b11 ,
b11 #
1"
#14171000
0"
#14189500
b100 #
b100 ,
1"
#14208000
0"
#14226500
b101 ,
b101 #
1"
#14245000
0"
#14263500
b110 #
b110 ,
1"
#14282000
0"
#14300500
b111 ,
b111 #
1"
#14319000
0"
#14337500
b1000 #
b1000 ,
1"
#14356000
0"
#14374500
b1001 ,
b1001 #
1"
#14393000
0"
#14411500
b1010 #
b1010 ,
1"
#14430000
0"
#14448500
b1011 ,
b1011 #
1"
#14467000
0"
#14485500
b1100 #
b1100 ,
1"
#14504000
0"
#14522500
b1101 ,
b1101 #
1"
#14541000
0"
#14559500
1!
b1110 #
b1110 ,
1"
#14578000
0"
#14596500
0!
b0 #
b0 ,
b11001 (
1"
#14615000
0"
#14633500
b1 ,
b1 #
1"
#14652000
0"
#14670500
b10 #
b10 ,
1"
#14689000
0"
#14707500
b11 ,
b11 #
1"
#14726000
0"
#14744500
b100 #
b100 ,
1"
#14763000
0"
#14781500
b101 ,
b101 #
1"
#14800000
0"
#14818500
b110 #
b110 ,
1"
#14837000
0"
#14855500
b111 ,
b111 #
1"
#14874000
0"
#14892500
b1000 #
b1000 ,
1"
#14911000
0"
#14929500
b1001 ,
b1001 #
1"
#14948000
0"
#14966500
b1010 #
b1010 ,
1"
#14985000
0"
#15003500
b1011 ,
b1011 #
1"
#15022000
0"
#15040500
b1100 #
b1100 ,
1"
#15059000
0"
#15077500
b1101 ,
b1101 #
1"
#15096000
0"
#15114500
1!
b1110 #
b1110 ,
1"
#15133000
0"
#15151500
0!
b0 #
b0 ,
b11010 (
1"
#15170000
0"
#15188500
b1 ,
b1 #
1"
#15207000
0"
#15225500
b10 #
b10 ,
1"
#15244000
0"
#15262500
b11 ,
b11 #
1"
#15281000
0"
#15299500
b100 #
b100 ,
1"
#15318000
0"
#15336500
b101 ,
b101 #
1"
#15355000
0"
#15373500
b110 #
b110 ,
1"
#15392000
0"
#15410500
b111 ,
b111 #
1"
#15429000
0"
#15447500
b1000 #
b1000 ,
1"
#15466000
0"
#15484500
b1001 ,
b1001 #
1"
#15503000
0"
#15521500
b1010 #
b1010 ,
1"
#15540000
0"
#15558500
b1011 ,
b1011 #
1"
#15577000
0"
#15595500
b1100 #
b1100 ,
1"
#15614000
0"
#15632500
b1101 ,
b1101 #
1"
#15651000
0"
#15669500
1!
b1110 #
b1110 ,
1"
#15688000
0"
#15706500
0!
b0 #
b0 ,
b11011 (
1"
#15725000
0"
#15743500
b1 ,
b1 #
1"
#15762000
0"
#15780500
b10 #
b10 ,
1"
#15799000
0"
#15817500
b11 ,
b11 #
1"
#15836000
0"
#15854500
b100 #
b100 ,
1"
#15873000
0"
#15891500
b101 ,
b101 #
1"
#15910000
0"
#15928500
b110 #
b110 ,
1"
#15947000
0"
#15965500
b111 ,
b111 #
1"
#15984000
0"
#16002500
b1000 #
b1000 ,
1"
#16021000
0"
#16039500
b1001 ,
b1001 #
1"
#16058000
0"
#16076500
b1010 #
b1010 ,
1"
#16095000
0"
#16113500
b1011 ,
b1011 #
1"
#16132000
0"
#16150500
b1100 #
b1100 ,
1"
#16169000
0"
#16187500
b1101 ,
b1101 #
1"
#16206000
0"
#16224500
1!
b1110 #
b1110 ,
1"
#16243000
0"
#16261500
0!
b0 #
b0 ,
b11100 (
1"
#16280000
0"
#16298500
b1 ,
b1 #
1"
#16317000
0"
#16335500
b10 #
b10 ,
1"
#16354000
0"
#16372500
b11 ,
b11 #
1"
#16391000
0"
#16409500
b100 #
b100 ,
1"
